{
"meta":{"test_sets":[],"test_metrics":[],"learn_metrics":[{"best_value":"Min","name":"RMSE"}],"launch_mode":"Train","parameters":"","iteration_count":1000,"learn_sets":["learn"],"name":"experiment"},
"iterations":[
{"learn":[3717.786335],"iteration":0,"passed_time":0.007642323807,"remaining_time":7.634681484},
{"learn":[3494.043523],"iteration":1,"passed_time":0.01628034895,"remaining_time":8.123894124},
{"learn":[3288.347314],"iteration":2,"passed_time":0.02497758169,"remaining_time":8.30088298},
{"learn":[3095.779014],"iteration":3,"passed_time":0.03100183333,"remaining_time":7.7194565},
{"learn":[2921.550837],"iteration":4,"passed_time":0.03571588575,"remaining_time":7.107461265},
{"learn":[2752.718084],"iteration":5,"passed_time":0.03996964926,"remaining_time":6.621638561},
{"learn":[2605.312648],"iteration":6,"passed_time":0.04625710714,"remaining_time":6.561901056},
{"learn":[2466.113997],"iteration":7,"passed_time":0.05120328201,"remaining_time":6.349206969},
{"learn":[2338.824709],"iteration":8,"passed_time":0.05585579285,"remaining_time":6.150343412},
{"learn":[2219.711026],"iteration":9,"passed_time":0.06260216466,"remaining_time":6.197614301},
{"learn":[2107.858201],"iteration":10,"passed_time":0.06844962549,"remaining_time":6.1542436},
{"learn":[2001.281478],"iteration":11,"passed_time":0.0726417224,"remaining_time":5.980835145},
{"learn":[1903.087599],"iteration":12,"passed_time":0.07675406986,"remaining_time":5.82740515},
{"learn":[1814.68788],"iteration":13,"passed_time":0.08043404521,"remaining_time":5.664854898},
{"learn":[1737.771088],"iteration":14,"passed_time":0.08425997758,"remaining_time":5.533071861},
{"learn":[1661.827003],"iteration":15,"passed_time":0.08750270586,"remaining_time":5.38141641},
{"learn":[1597.067979],"iteration":16,"passed_time":0.09117059829,"remaining_time":5.271805772},
{"learn":[1537.017414],"iteration":17,"passed_time":0.09459686734,"remaining_time":5.160784651},
{"learn":[1478.452409],"iteration":18,"passed_time":0.09787417838,"remaining_time":5.053398368},
{"learn":[1427.874133],"iteration":19,"passed_time":0.1016901528,"remaining_time":4.982817488},
{"learn":[1382.720244],"iteration":20,"passed_time":0.1049372971,"remaining_time":4.892076849},
{"learn":[1336.7773],"iteration":21,"passed_time":0.10823865,"remaining_time":4.811699984},
{"learn":[1297.659375],"iteration":22,"passed_time":0.1114123787,"remaining_time":4.732604086},
{"learn":[1257.746159],"iteration":23,"passed_time":0.1142834015,"remaining_time":4.647524993},
{"learn":[1223.559295],"iteration":24,"passed_time":0.1167546349,"remaining_time":4.553430762},
{"learn":[1187.103236],"iteration":25,"passed_time":0.1195406162,"remaining_time":4.478175393},
{"learn":[1156.373249],"iteration":26,"passed_time":0.1226039707,"remaining_time":4.418283834},
{"learn":[1127.254381],"iteration":27,"passed_time":0.1254367858,"remaining_time":4.35444842},
{"learn":[1103.759378],"iteration":28,"passed_time":0.1279800187,"remaining_time":4.285124075},
{"learn":[1077.23332],"iteration":29,"passed_time":0.1307048755,"remaining_time":4.226124307},
{"learn":[1057.516864],"iteration":30,"passed_time":0.1334970228,"remaining_time":4.17285855},
{"learn":[1036.009696],"iteration":31,"passed_time":0.1369473746,"remaining_time":4.142658083},
{"learn":[1013.437858],"iteration":32,"passed_time":0.1400908946,"remaining_time":4.105087729},
{"learn":[997.3122489],"iteration":33,"passed_time":0.1433665806,"remaining_time":4.073297556},
{"learn":[980.1741731],"iteration":34,"passed_time":0.1467653909,"remaining_time":4.046531491},
{"learn":[965.8139373],"iteration":35,"passed_time":0.1492103335,"remaining_time":3.995521153},
{"learn":[947.6173593],"iteration":36,"passed_time":0.1522211463,"remaining_time":3.96186389},
{"learn":[933.0723649],"iteration":37,"passed_time":0.1557186649,"remaining_time":3.942140938},
{"learn":[919.1168544],"iteration":38,"passed_time":0.1589098105,"remaining_time":3.915700716},
{"learn":[907.1976137],"iteration":39,"passed_time":0.1623566624,"remaining_time":3.896559899},
{"learn":[895.103643],"iteration":40,"passed_time":0.1651533517,"remaining_time":3.862977178},
{"learn":[881.7796614],"iteration":41,"passed_time":0.1679336661,"remaining_time":3.830486955},
{"learn":[870.7540137],"iteration":42,"passed_time":0.1706168561,"remaining_time":3.797217007},
{"learn":[858.3476473],"iteration":43,"passed_time":0.173914792,"remaining_time":3.778694118},
{"learn":[848.1022948],"iteration":44,"passed_time":0.1768628553,"remaining_time":3.753422817},
{"learn":[839.189244],"iteration":45,"passed_time":0.1799505016,"remaining_time":3.732016924},
{"learn":[830.1667167],"iteration":46,"passed_time":0.1825639841,"remaining_time":3.701776103},
{"learn":[821.7409077],"iteration":47,"passed_time":0.1851323839,"remaining_time":3.67179228},
{"learn":[813.1128552],"iteration":48,"passed_time":0.187658867,"remaining_time":3.642113928},
{"learn":[805.2014394],"iteration":49,"passed_time":0.1908187628,"remaining_time":3.625556493},
{"learn":[797.9242549],"iteration":50,"passed_time":0.1935713273,"remaining_time":3.601944895},
{"learn":[791.6097747],"iteration":51,"passed_time":0.1965476404,"remaining_time":3.583214675},
{"learn":[783.9976765],"iteration":52,"passed_time":0.1993157049,"remaining_time":3.561357972},
{"learn":[777.4651674],"iteration":53,"passed_time":0.2018662708,"remaining_time":3.536398003},
{"learn":[772.0171053],"iteration":54,"passed_time":0.2048297089,"remaining_time":3.519346817},
{"learn":[766.9974089],"iteration":55,"passed_time":0.2077378145,"remaining_time":3.501866015},
{"learn":[761.1416429],"iteration":56,"passed_time":0.2104784211,"remaining_time":3.482125458},
{"learn":[756.920128],"iteration":57,"passed_time":0.2130792787,"remaining_time":3.460701388},
{"learn":[752.5354896],"iteration":58,"passed_time":0.2157880105,"remaining_time":3.441635897},
{"learn":[748.0629591],"iteration":59,"passed_time":0.2182897018,"remaining_time":3.419871994},
{"learn":[744.5334635],"iteration":60,"passed_time":0.2210809331,"remaining_time":3.403196658},
{"learn":[740.7062974],"iteration":61,"passed_time":0.2239984545,"remaining_time":3.388879844},
{"learn":[736.7762999],"iteration":62,"passed_time":0.2267839769,"remaining_time":3.372961688},
{"learn":[732.0029243],"iteration":63,"passed_time":0.2293265428,"remaining_time":3.353900689},
{"learn":[727.8876349],"iteration":64,"passed_time":0.2318696508,"remaining_time":3.335355746},
{"learn":[724.1737943],"iteration":65,"passed_time":0.2347657564,"remaining_time":3.322291159},
{"learn":[719.6866759],"iteration":66,"passed_time":0.2373333642,"remaining_time":3.304955654},
{"learn":[715.984448],"iteration":67,"passed_time":0.2396364318,"remaining_time":3.284428741},
{"learn":[712.6973822],"iteration":68,"passed_time":0.2423594135,"remaining_time":3.270095855},
{"learn":[710.3186809],"iteration":69,"passed_time":0.2448516468,"remaining_time":3.253029022},
{"learn":[706.6738348],"iteration":70,"passed_time":0.247512629,"remaining_time":3.238580737},
{"learn":[703.9661982],"iteration":71,"passed_time":0.2500233202,"remaining_time":3.222522794},
{"learn":[700.6308026],"iteration":72,"passed_time":0.2527095932,"remaining_time":3.209065656},
{"learn":[696.6280048],"iteration":73,"passed_time":0.2552442432,"remaining_time":3.194002287},
{"learn":[694.2312804],"iteration":74,"passed_time":0.2577584764,"remaining_time":3.179021209},
{"learn":[692.1787953],"iteration":75,"passed_time":0.2603055423,"remaining_time":3.164767383},
{"learn":[689.0075275],"iteration":76,"passed_time":0.2627717338,"remaining_time":3.149848186},
{"learn":[686.7107144],"iteration":77,"passed_time":0.2652420923,"remaining_time":3.135297552},
{"learn":[684.2832523],"iteration":78,"passed_time":0.2678877835,"remaining_time":3.123096818},
{"learn":[682.8580927],"iteration":79,"passed_time":0.2705264749,"remaining_time":3.111054461},
{"learn":[679.5129219],"iteration":80,"passed_time":0.2730317911,"remaining_time":3.097731062},
{"learn":[675.623168],"iteration":81,"passed_time":0.2756571895,"remaining_time":3.086015853},
{"learn":[673.4538029],"iteration":82,"passed_time":0.2780749233,"remaining_time":3.072225357},
{"learn":[671.7708421],"iteration":83,"passed_time":0.280655281,"remaining_time":3.060479017},
{"learn":[669.3200546],"iteration":84,"passed_time":0.2830593069,"remaining_time":3.047050186},
{"learn":[665.9524965],"iteration":85,"passed_time":0.2855499562,"remaining_time":3.034798372},
{"learn":[663.2103238],"iteration":86,"passed_time":0.2883918952,"remaining_time":3.026457475},
{"learn":[661.7088537],"iteration":87,"passed_time":0.2908370458,"remaining_time":3.014129384},
{"learn":[660.4589851],"iteration":88,"passed_time":0.2937695682,"remaining_time":3.007012097},
{"learn":[658.3534207],"iteration":89,"passed_time":0.2962914263,"remaining_time":2.995835532},
{"learn":[657.1963866],"iteration":90,"passed_time":0.2987399519,"remaining_time":2.984116662},
{"learn":[654.3852385],"iteration":91,"passed_time":0.3014526417,"remaining_time":2.975206507},
{"learn":[652.7827906],"iteration":92,"passed_time":0.303797418,"remaining_time":2.962841485},
{"learn":[650.0565701],"iteration":93,"passed_time":0.3060571109,"remaining_time":2.9498696},
{"learn":[647.8147171],"iteration":94,"passed_time":0.3086245937,"remaining_time":2.94005534},
{"learn":[645.8138757],"iteration":95,"passed_time":0.31095612,"remaining_time":2.92817013},
{"learn":[644.2156431],"iteration":96,"passed_time":0.3135205609,"remaining_time":2.91865017},
{"learn":[642.1706081],"iteration":97,"passed_time":0.3162059179,"remaining_time":2.910385081},
{"learn":[640.0259039],"iteration":98,"passed_time":0.3190073571,"remaining_time":2.903289179},
{"learn":[638.8881922],"iteration":99,"passed_time":0.3217360478,"remaining_time":2.89562443},
{"learn":[637.2062789],"iteration":100,"passed_time":0.3244294048,"remaining_time":2.88774292},
{"learn":[635.9914601],"iteration":101,"passed_time":0.3271435536,"remaining_time":2.880146188},
{"learn":[634.8225542],"iteration":102,"passed_time":0.3296894116,"remaining_time":2.871178662},
{"learn":[633.236848],"iteration":103,"passed_time":0.3325093087,"remaining_time":2.864695582},
{"learn":[631.6653001],"iteration":104,"passed_time":0.3349395014,"remaining_time":2.854960512},
{"learn":[630.2424606],"iteration":105,"passed_time":0.3374808174,"remaining_time":2.846300479},
{"learn":[628.3647843],"iteration":106,"passed_time":0.3400895079,"remaining_time":2.838317108},
{"learn":[627.7329171],"iteration":107,"passed_time":0.3424114503,"remaining_time":2.828064942},
{"learn":[626.3820497],"iteration":108,"passed_time":0.345000516,"remaining_time":2.820141833},
{"learn":[625.4752778],"iteration":109,"passed_time":0.3475799987,"remaining_time":2.812238171},
{"learn":[623.6725093],"iteration":110,"passed_time":0.3503078134,"remaining_time":2.805618434},
{"learn":[621.6412375],"iteration":111,"passed_time":0.3531681273,"remaining_time":2.800118723},
{"learn":[619.9577409],"iteration":112,"passed_time":0.3554762368,"remaining_time":2.790331169},
{"learn":[617.6512689],"iteration":113,"passed_time":0.3578782207,"remaining_time":2.781404417},
{"learn":[616.579387],"iteration":114,"passed_time":0.3603874539,"remaining_time":2.773416493},
{"learn":[615.0166471],"iteration":115,"passed_time":0.3629923945,"remaining_time":2.766252385},
{"learn":[613.6981859],"iteration":116,"passed_time":0.3653829615,"remaining_time":2.757548333},
{"learn":[612.3971669],"iteration":117,"passed_time":0.3679971519,"remaining_time":2.75062278},
{"learn":[611.7171871],"iteration":118,"passed_time":0.3703253034,"remaining_time":2.741652036},
{"learn":[611.1052905],"iteration":119,"passed_time":0.3723878725,"remaining_time":2.730844399},
{"learn":[610.2972478],"iteration":120,"passed_time":0.3747791895,"remaining_time":2.722569484},
{"learn":[609.1329892],"iteration":121,"passed_time":0.3773291724,"remaining_time":2.715532897},
{"learn":[607.740679],"iteration":122,"passed_time":0.3800599881,"remaining_time":2.709858615},
{"learn":[605.9252529],"iteration":123,"passed_time":0.3825075547,"remaining_time":2.70223079},
{"learn":[604.8090449],"iteration":124,"passed_time":0.3852344535,"remaining_time":2.696641174},
{"learn":[604.2359621],"iteration":125,"passed_time":0.3877499776,"remaining_time":2.689630797},
{"learn":[602.5989609],"iteration":126,"passed_time":0.3903055855,"remaining_time":2.682966741},
{"learn":[601.8032108],"iteration":127,"passed_time":0.3929926095,"remaining_time":2.677262152},
{"learn":[600.7790627],"iteration":128,"passed_time":0.3958242985,"remaining_time":2.672581117},
{"learn":[600.1219511],"iteration":129,"passed_time":0.3983699905,"remaining_time":2.666014552},
{"learn":[599.0590235],"iteration":130,"passed_time":0.4008870986,"remaining_time":2.659319761},
{"learn":[598.1211885],"iteration":131,"passed_time":0.4034634974,"remaining_time":2.653078149},
{"learn":[597.3354783],"iteration":132,"passed_time":0.4058304815,"remaining_time":2.645526522},
{"learn":[596.3405581],"iteration":133,"passed_time":0.4083387987,"remaining_time":2.638965669},
{"learn":[595.9027967],"iteration":134,"passed_time":0.4107697824,"remaining_time":2.631969347},
{"learn":[594.8106706],"iteration":135,"passed_time":0.4135524718,"remaining_time":2.627274527},
{"learn":[594.3255258],"iteration":136,"passed_time":0.4162226629,"remaining_time":2.621898964},
{"learn":[592.8200897],"iteration":137,"passed_time":0.4191739351,"remaining_time":2.618318348},
{"learn":[591.8332939],"iteration":138,"passed_time":0.4222031648,"remaining_time":2.615229676},
{"learn":[591.1366191],"iteration":139,"passed_time":0.4248173553,"remaining_time":2.609592326},
{"learn":[590.358887],"iteration":140,"passed_time":0.4275334621,"remaining_time":2.604618752},
{"learn":[589.9161236],"iteration":141,"passed_time":0.4303016096,"remaining_time":2.599991416},
{"learn":[588.8145789],"iteration":142,"passed_time":0.433524588,"remaining_time":2.598115888},
{"learn":[588.1113333],"iteration":143,"passed_time":0.4363368602,"remaining_time":2.593780224},
{"learn":[587.2293288],"iteration":144,"passed_time":0.4396828798,"remaining_time":2.592612843},
{"learn":[586.7400389],"iteration":145,"passed_time":0.4422037379,"remaining_time":2.586588987},
{"learn":[585.9849032],"iteration":146,"passed_time":0.4446966792,"remaining_time":2.580450798},
{"learn":[585.0355016],"iteration":147,"passed_time":0.4472856198,"remaining_time":2.574914514},
{"learn":[584.5006246],"iteration":148,"passed_time":0.4496698959,"remaining_time":2.568248868},
{"learn":[583.7352628],"iteration":149,"passed_time":0.4519963383,"remaining_time":2.561312584},
{"learn":[583.4325058],"iteration":150,"passed_time":0.4549884432,"remaining_time":2.558180055},
{"learn":[582.2617366],"iteration":151,"passed_time":0.4585419194,"remaining_time":2.558181235},
{"learn":[581.5618895],"iteration":152,"passed_time":0.4615675652,"remaining_time":2.555213906},
{"learn":[580.9323668],"iteration":153,"passed_time":0.4648913349,"remaining_time":2.553883567},
{"learn":[579.4269198],"iteration":154,"passed_time":0.4673624853,"remaining_time":2.547879356},
{"learn":[578.2473316],"iteration":155,"passed_time":0.4699859678,"remaining_time":2.542744595},
{"learn":[576.9952315],"iteration":156,"passed_time":0.4731178628,"remaining_time":2.540371709},
{"learn":[576.3736897],"iteration":157,"passed_time":0.4757480952,"remaining_time":2.535315798},
{"learn":[575.615749],"iteration":158,"passed_time":0.4782520784,"remaining_time":2.529622629},
{"learn":[574.982808],"iteration":159,"passed_time":0.4811001013,"remaining_time":2.525775532},
{"learn":[574.1399443],"iteration":160,"passed_time":0.4835502099,"remaining_time":2.519867243},
{"learn":[573.3860362],"iteration":161,"passed_time":0.4862341509,"remaining_time":2.515211225},
{"learn":[572.7987855],"iteration":162,"passed_time":0.4888435504,"remaining_time":2.510196636},
{"learn":[572.1629117],"iteration":163,"passed_time":0.4913940334,"remaining_time":2.504911048},
{"learn":[571.6015212],"iteration":164,"passed_time":0.4942326804,"remaining_time":2.501116898},
{"learn":[571.2131203],"iteration":165,"passed_time":0.4965593738,"remaining_time":2.494762155},
{"learn":[571.0784132],"iteration":166,"passed_time":0.4990070244,"remaining_time":2.48905899},
{"learn":[570.4472886],"iteration":167,"passed_time":0.5016572566,"remaining_time":2.484397842},
{"learn":[570.0793124],"iteration":168,"passed_time":0.5043690305,"remaining_time":2.480063102},
{"learn":[569.5553997],"iteration":169,"passed_time":0.5071534708,"remaining_time":2.47610224},
{"learn":[569.3116807],"iteration":170,"passed_time":0.5097001617,"remaining_time":2.471002538},
{"learn":[568.7970335],"iteration":171,"passed_time":0.5120938957,"remaining_time":2.465196196},
{"learn":[567.7574219],"iteration":172,"passed_time":0.5147748777,"remaining_time":2.46080245},
{"learn":[567.2175702],"iteration":173,"passed_time":0.5175434842,"remaining_time":2.456844356},
{"learn":[566.7053125],"iteration":174,"passed_time":0.5203952561,"remaining_time":2.453291922},
{"learn":[566.5492521],"iteration":175,"passed_time":0.5229641139,"remaining_time":2.448422897},
{"learn":[565.8663466],"iteration":176,"passed_time":0.5255836383,"remaining_time":2.443815448},
{"learn":[565.2687758],"iteration":177,"passed_time":0.5280718307,"remaining_time":2.438623847},
{"learn":[564.7538643],"iteration":178,"passed_time":0.5304786896,"remaining_time":2.433089409},
{"learn":[564.3345491],"iteration":179,"passed_time":0.5329422981,"remaining_time":2.427848247},
{"learn":[562.8410233],"iteration":180,"passed_time":0.5357305294,"remaining_time":2.424106649},
{"learn":[562.4024944],"iteration":181,"passed_time":0.5383138041,"remaining_time":2.41945435},
{"learn":[561.8879917],"iteration":182,"passed_time":0.5407944125,"remaining_time":2.414366311},
{"learn":[561.304989],"iteration":183,"passed_time":0.543104731,"remaining_time":2.408551416},
{"learn":[560.9325577],"iteration":184,"passed_time":0.5457639632,"remaining_time":2.404311513},
{"learn":[560.4890868],"iteration":185,"passed_time":0.5483936545,"remaining_time":2.399959327},
{"learn":[560.0614762],"iteration":186,"passed_time":0.5508116794,"remaining_time":2.394705323},
{"learn":[559.1756598],"iteration":187,"passed_time":0.5533603293,"remaining_time":2.390045678},
{"learn":[558.4535968],"iteration":188,"passed_time":0.555797396,"remaining_time":2.384929567},
{"learn":[558.2309958],"iteration":189,"passed_time":0.5579370896,"remaining_time":2.378573908},
{"learn":[557.9731311],"iteration":190,"passed_time":0.5602395332,"remaining_time":2.37295174},
{"learn":[557.6047315],"iteration":191,"passed_time":0.562954473,"remaining_time":2.369100074},
{"learn":[557.0047107],"iteration":192,"passed_time":0.5653557899,"remaining_time":2.363948821},
{"learn":[556.8760194],"iteration":193,"passed_time":0.5677439399,"remaining_time":2.358771214},
{"learn":[556.3471549],"iteration":194,"passed_time":0.5702799639,"remaining_time":2.354232672},
{"learn":[555.9786158],"iteration":195,"passed_time":0.5728465718,"remaining_time":2.349840019},
{"learn":[555.8154433],"iteration":196,"passed_time":0.5751625152,"remaining_time":2.344444161},
{"learn":[555.4899571],"iteration":197,"passed_time":0.5779266637,"remaining_time":2.34089487},
{"learn":[554.6480307],"iteration":198,"passed_time":0.5804338139,"remaining_time":2.33631902},
{"learn":[554.0425602],"iteration":199,"passed_time":0.5827047567,"remaining_time":2.330819027},
{"learn":[553.1081888],"iteration":200,"passed_time":0.5856212792,"remaining_time":2.327917423},
{"learn":[552.727174],"iteration":201,"passed_time":0.588189846,"remaining_time":2.323641075},
{"learn":[552.2555777],"iteration":202,"passed_time":0.590868411,"remaining_time":2.319813417},
{"learn":[551.9970115],"iteration":203,"passed_time":0.5935217683,"remaining_time":2.315898664},
{"learn":[551.595223],"iteration":204,"passed_time":0.5961443347,"remaining_time":2.31187681},
{"learn":[550.8424048],"iteration":205,"passed_time":0.5985370687,"remaining_time":2.306982682},
{"learn":[550.4039739],"iteration":206,"passed_time":0.6007643457,"remaining_time":2.30147887},
{"learn":[549.8840007],"iteration":207,"passed_time":0.6034465368,"remaining_time":2.297738736},
{"learn":[549.4956306],"iteration":208,"passed_time":0.6060711022,"remaining_time":2.293790631},
{"learn":[548.9059279],"iteration":209,"passed_time":0.6084564612,"remaining_time":2.288955259},
{"learn":[548.7357106],"iteration":210,"passed_time":0.6110072771,"remaining_time":2.284761809},
{"learn":[548.5002078],"iteration":211,"passed_time":0.6135331352,"remaining_time":2.280491087},
{"learn":[548.3514084],"iteration":212,"passed_time":0.6159681189,"remaining_time":2.275900984},
{"learn":[547.8573719],"iteration":213,"passed_time":0.6188261418,"remaining_time":2.272884801},
{"learn":[547.5370504],"iteration":214,"passed_time":0.6212364596,"remaining_time":2.268235446},
{"learn":[547.065824],"iteration":215,"passed_time":0.6236417355,"remaining_time":2.263588521},
{"learn":[546.9555451],"iteration":216,"passed_time":0.6259686359,"remaining_time":2.258679456},
{"learn":[546.5293641],"iteration":217,"passed_time":0.6282433297,"remaining_time":2.253606806},
{"learn":[545.7752297],"iteration":218,"passed_time":0.6309390616,"remaining_time":2.25006122},
{"learn":[545.4190233],"iteration":219,"passed_time":0.6332794209,"remaining_time":2.245263402},
{"learn":[545.042147],"iteration":220,"passed_time":0.6357572793,"remaining_time":2.240972491},
{"learn":[544.7038796],"iteration":221,"passed_time":0.6383575119,"remaining_time":2.237126776},
{"learn":[543.7199485],"iteration":222,"passed_time":0.6408132045,"remaining_time":2.232788609},
{"learn":[543.3565971],"iteration":223,"passed_time":0.6433398535,"remaining_time":2.228713064},
{"learn":[543.2055274],"iteration":224,"passed_time":0.6458337538,"remaining_time":2.224538485},
{"learn":[542.7586209],"iteration":225,"passed_time":0.6483144042,"remaining_time":2.220333402},
{"learn":[541.6256637],"iteration":226,"passed_time":0.6506823884,"remaining_time":2.215759851},
{"learn":[541.2407679],"iteration":227,"passed_time":0.6531020802,"remaining_time":2.211380728},
{"learn":[540.9618555],"iteration":228,"passed_time":0.6558213119,"remaining_time":2.208027212},
{"learn":[540.6247531],"iteration":229,"passed_time":0.6584631692,"remaining_time":2.204420175},
{"learn":[540.2226362],"iteration":230,"passed_time":0.6608141535,"remaining_time":2.199853178},
{"learn":[539.9985502],"iteration":231,"passed_time":0.6633500955,"remaining_time":2.195917558},
{"learn":[539.9041586],"iteration":232,"passed_time":0.665811537,"remaining_time":2.191748708},
{"learn":[539.5869079],"iteration":233,"passed_time":0.6683768528,"remaining_time":2.187934484},
{"learn":[538.6080664],"iteration":234,"passed_time":0.6710882927,"remaining_time":2.18460657},
{"learn":[538.4664684],"iteration":235,"passed_time":0.6736930672,"remaining_time":2.180938574},
{"learn":[538.1618801],"iteration":236,"passed_time":0.6762798829,"remaining_time":2.177221733},
{"learn":[537.8237881],"iteration":237,"passed_time":0.6787919081,"remaining_time":2.173274933},
{"learn":[537.1235268],"iteration":238,"passed_time":0.6814315564,"remaining_time":2.169746504},
{"learn":[536.8740844],"iteration":239,"passed_time":0.6839246227,"remaining_time":2.165761305},
{"learn":[536.1282056],"iteration":240,"passed_time":0.6865431051,"remaining_time":2.162183472},
{"learn":[535.7587845],"iteration":241,"passed_time":0.6891419627,"remaining_time":2.158552098},
{"learn":[535.4355187],"iteration":242,"passed_time":0.6914172815,"remaining_time":2.153921325},
{"learn":[535.0427483],"iteration":243,"passed_time":0.6940026812,"remaining_time":2.150270602},
{"learn":[534.8294949],"iteration":244,"passed_time":0.6963427905,"remaining_time":2.145872681},
{"learn":[534.5958205],"iteration":245,"passed_time":0.6988640236,"remaining_time":2.142046641},
{"learn":[534.4537048],"iteration":246,"passed_time":0.7015203808,"remaining_time":2.138643104},
{"learn":[534.1695668],"iteration":247,"passed_time":0.7039313227,"remaining_time":2.13450143},
{"learn":[533.8988883],"iteration":248,"passed_time":0.70656993,"remaining_time":2.131060311},
{"learn":[533.7300953],"iteration":249,"passed_time":0.7092782449,"remaining_time":2.127834735},
{"learn":[533.3862317],"iteration":250,"passed_time":0.7118107689,"remaining_time":2.124088709},
{"learn":[532.7709594],"iteration":251,"passed_time":0.7142988352,"remaining_time":2.120220352},
{"learn":[532.409458],"iteration":252,"passed_time":0.7169545254,"remaining_time":2.116857828},
{"learn":[532.2720155],"iteration":253,"passed_time":0.7193963421,"remaining_time":2.112872721},
{"learn":[531.9998966],"iteration":254,"passed_time":0.7222258641,"remaining_time":2.110032427},
{"learn":[531.6942652],"iteration":255,"passed_time":0.7244724741,"remaining_time":2.105498128},
{"learn":[531.4768428],"iteration":256,"passed_time":0.7269670414,"remaining_time":2.101698489},
{"learn":[530.9552595],"iteration":257,"passed_time":0.7296241076,"remaining_time":2.098376309},
{"learn":[530.583771],"iteration":258,"passed_time":0.7319642169,"remaining_time":2.094152451},
{"learn":[530.3654516],"iteration":259,"passed_time":0.7343243681,"remaining_time":2.090000125},
{"learn":[530.0398031],"iteration":260,"passed_time":0.7371435152,"remaining_time":2.087161141},
{"learn":[529.7674806],"iteration":261,"passed_time":0.7395841238,"remaining_time":2.083256044},
{"learn":[529.3760368],"iteration":262,"passed_time":0.742245231,"remaining_time":2.079979982},
{"learn":[528.8926842],"iteration":263,"passed_time":0.7449878377,"remaining_time":2.07693579},
{"learn":[528.5549888],"iteration":264,"passed_time":0.7472444055,"remaining_time":2.072545804},
{"learn":[528.2287607],"iteration":265,"passed_time":0.74985943,"remaining_time":2.069160984},
{"learn":[527.9673794],"iteration":266,"passed_time":0.7524113299,"remaining_time":2.065608632},
{"learn":[527.8481058],"iteration":267,"passed_time":0.754940479,"remaining_time":2.062001607},
{"learn":[527.465741],"iteration":268,"passed_time":0.7574953369,"remaining_time":2.058472458},
{"learn":[527.1945638],"iteration":269,"passed_time":0.7600790696,"remaining_time":2.055028595},
{"learn":[527.0873723],"iteration":270,"passed_time":0.7624395127,"remaining_time":2.050990424},
{"learn":[526.8369214],"iteration":271,"passed_time":0.7652102862,"remaining_time":2.048062825},
{"learn":[526.5702597],"iteration":272,"passed_time":0.7677911019,"remaining_time":2.044630517},
{"learn":[526.288057],"iteration":273,"passed_time":0.7701747519,"remaining_time":2.040682007},
{"learn":[525.9572144],"iteration":274,"passed_time":0.7727753175,"remaining_time":2.037316746},
{"learn":[525.5529783],"iteration":275,"passed_time":0.7754705495,"remaining_time":2.034205354},
{"learn":[525.3603371],"iteration":276,"passed_time":0.7781287397,"remaining_time":2.031000284},
{"learn":[525.195449],"iteration":277,"passed_time":0.7805252656,"remaining_time":2.027119575},
{"learn":[524.9589026],"iteration":278,"passed_time":0.7830933734,"remaining_time":2.023692911},
{"learn":[524.7215237],"iteration":279,"passed_time":0.7857776474,"remaining_time":2.020571093},
{"learn":[524.4242954],"iteration":280,"passed_time":0.788378463,"remaining_time":2.017238843},
{"learn":[523.9546253],"iteration":281,"passed_time":0.7908965301,"remaining_time":2.013701094},
{"learn":[523.7063234],"iteration":282,"passed_time":0.7934888038,"remaining_time":2.010358559},
{"learn":[523.3624628],"iteration":283,"passed_time":0.7958779538,"remaining_time":2.006509207},
{"learn":[523.0883194],"iteration":284,"passed_time":0.7984788113,"remaining_time":2.003201228},
{"learn":[522.7420886],"iteration":285,"passed_time":0.801363792,"remaining_time":2.000607509},
{"learn":[522.4377658],"iteration":286,"passed_time":0.8041189826,"remaining_time":1.997689319},
{"learn":[522.147168],"iteration":287,"passed_time":0.8064666328,"remaining_time":1.993764731},
{"learn":[521.9026885],"iteration":288,"passed_time":0.8092647811,"remaining_time":1.990959375},
{"learn":[521.5932775],"iteration":289,"passed_time":0.8117629734,"remaining_time":1.987419693},
{"learn":[521.3887385],"iteration":290,"passed_time":0.8143277892,"remaining_time":1.984049493},
{"learn":[521.1927413],"iteration":291,"passed_time":0.8166603565,"remaining_time":1.980121686},
{"learn":[520.9325813],"iteration":292,"passed_time":0.8191944646,"remaining_time":1.97669108},
{"learn":[520.7576422],"iteration":293,"passed_time":0.8217929052,"remaining_time":1.973421058},
{"learn":[520.4908151],"iteration":294,"passed_time":0.8243246382,"remaining_time":1.969996169},
{"learn":[520.1951882],"iteration":295,"passed_time":0.827045912,"remaining_time":1.967028115},
{"learn":[520.0038349],"iteration":296,"passed_time":0.8298363103,"remaining_time":1.964225341},
{"learn":[519.7317835],"iteration":297,"passed_time":0.8328167903,"remaining_time":1.961870426},
{"learn":[519.407507],"iteration":298,"passed_time":0.8353169406,"remaining_time":1.958385202},
{"learn":[519.1786919],"iteration":299,"passed_time":0.8378965483,"remaining_time":1.955091946},
{"learn":[518.9440055],"iteration":300,"passed_time":0.8406910716,"remaining_time":1.952302522},
{"learn":[518.8830696],"iteration":301,"passed_time":0.8433603457,"remaining_time":1.94922358},
{"learn":[518.6542647],"iteration":302,"passed_time":0.8461987847,"remaining_time":1.946536478},
{"learn":[518.3804688],"iteration":303,"passed_time":0.8488758508,"remaining_time":1.943478921},
{"learn":[518.0959767],"iteration":304,"passed_time":0.8518889556,"remaining_time":1.941189587},
{"learn":[517.8400394],"iteration":305,"passed_time":0.8546919788,"remaining_time":1.938419063},
{"learn":[517.5973017],"iteration":306,"passed_time":0.8572374617,"remaining_time":1.935066974},
{"learn":[517.3395487],"iteration":307,"passed_time":0.8598399023,"remaining_time":1.931848092},
{"learn":[517.046086],"iteration":308,"passed_time":0.8626437585,"remaining_time":1.929083615},
{"learn":[516.8123354],"iteration":309,"passed_time":0.8651294089,"remaining_time":1.92561062},
{"learn":[516.6247571],"iteration":310,"passed_time":0.8673411441,"remaining_time":1.921537133},
{"learn":[516.3971137],"iteration":311,"passed_time":0.8697786277,"remaining_time":1.917973384},
{"learn":[516.1644829],"iteration":312,"passed_time":0.8722446522,"remaining_time":1.914479476},
{"learn":[515.9646196],"iteration":313,"passed_time":0.8746988858,"remaining_time":1.910966356},
{"learn":[515.9007875],"iteration":314,"passed_time":0.8772220359,"remaining_time":1.907609824},
{"learn":[515.6962552],"iteration":315,"passed_time":0.87944873,"remaining_time":1.903616871},
{"learn":[515.6193745],"iteration":316,"passed_time":0.8822212944,"remaining_time":1.90081118},
{"learn":[515.4417952],"iteration":317,"passed_time":0.8849366932,"remaining_time":1.897883097},
{"learn":[515.2483469],"iteration":318,"passed_time":0.8874130096,"remaining_time":1.894445955},
{"learn":[514.7264014],"iteration":319,"passed_time":0.8899366177,"remaining_time":1.891115313},
{"learn":[514.4043133],"iteration":320,"passed_time":0.8926085998,"remaining_time":1.888103549},
{"learn":[514.2307384],"iteration":321,"passed_time":0.8952234983,"remaining_time":1.884973701},
{"learn":[513.9937818],"iteration":322,"passed_time":0.8978766475,"remaining_time":1.881927215},
{"learn":[513.6723929],"iteration":323,"passed_time":0.9002595066,"remaining_time":1.878319217},
{"learn":[513.42823],"iteration":324,"passed_time":0.9027524069,"remaining_time":1.874947307},
{"learn":[513.0250384],"iteration":325,"passed_time":0.9052210153,"remaining_time":1.871530565},
{"learn":[512.8029559],"iteration":326,"passed_time":0.9078954134,"remaining_time":1.86854316},
{"learn":[512.7127161],"iteration":327,"passed_time":0.9103983546,"remaining_time":1.865206385},
{"learn":[512.4666531],"iteration":328,"passed_time":0.9128930049,"remaining_time":1.86185777},
{"learn":[512.2722439],"iteration":329,"passed_time":0.9153801133,"remaining_time":1.858499018},
{"learn":[512.0445308],"iteration":330,"passed_time":0.9183540103,"remaining_time":1.856129405},
{"learn":[511.8571494],"iteration":331,"passed_time":0.920941868,"remaining_time":1.852979421},
{"learn":[511.6854785],"iteration":332,"passed_time":0.9234559762,"remaining_time":1.849685093},
{"learn":[511.406199],"iteration":333,"passed_time":0.9258064184,"remaining_time":1.846069086},
{"learn":[511.222239],"iteration":334,"passed_time":0.928555609,"remaining_time":1.843252179},
{"learn":[511.1787362],"iteration":335,"passed_time":0.9310715512,"remaining_time":1.839974732},
{"learn":[510.9462492],"iteration":336,"passed_time":0.9335761594,"remaining_time":1.836679506},
{"learn":[510.7158656],"iteration":337,"passed_time":0.9362451825,"remaining_time":1.833710979},
{"learn":[510.5350399],"iteration":338,"passed_time":0.9390358298,"remaining_time":1.830981367},
{"learn":[510.3537842],"iteration":339,"passed_time":0.9414751475,"remaining_time":1.827569404},
{"learn":[509.9239383],"iteration":340,"passed_time":0.9440472972,"remaining_time":1.82441985},
{"learn":[509.7613886],"iteration":341,"passed_time":0.9467849449,"remaining_time":1.821592087},
{"learn":[509.6756658],"iteration":342,"passed_time":0.9493610946,"remaining_time":1.818455508},
{"learn":[509.4596907],"iteration":343,"passed_time":0.952144743,"remaining_time":1.815717882},
{"learn":[509.3644248],"iteration":344,"passed_time":0.954380186,"remaining_time":1.811939194},
{"learn":[509.1877836],"iteration":345,"passed_time":0.9567925869,"remaining_time":1.808503907},
{"learn":[508.8786739],"iteration":346,"passed_time":0.9594795689,"remaining_time":1.805591235},
{"learn":[508.6456564],"iteration":347,"passed_time":0.9618005533,"remaining_time":1.80199414},
{"learn":[508.3993971],"iteration":348,"passed_time":0.9641393287,"remaining_time":1.798437544},
{"learn":[508.1077098],"iteration":349,"passed_time":0.9668504775,"remaining_time":1.795579458},
{"learn":[507.8509646],"iteration":350,"passed_time":0.9693282529,"remaining_time":1.792290701},
{"learn":[507.6262184],"iteration":351,"passed_time":0.9720316928,"remaining_time":1.78942198},
{"learn":[507.4742064],"iteration":352,"passed_time":0.9749321324,"remaining_time":1.786915268},
{"learn":[507.3645166],"iteration":353,"passed_time":0.977527615,"remaining_time":1.783849828},
{"learn":[506.7195959],"iteration":354,"passed_time":0.980216014,"remaining_time":1.780955856},
{"learn":[506.4640702],"iteration":355,"passed_time":0.9827253722,"remaining_time":1.777739156},
{"learn":[506.2095005],"iteration":356,"passed_time":0.9854113542,"remaining_time":1.77484454},
{"learn":[505.9837762],"iteration":357,"passed_time":0.9879361702,"remaining_time":1.771662071},
{"learn":[505.6870046],"iteration":358,"passed_time":0.9908573177,"remaining_time":1.769190921},
{"learn":[505.5369411],"iteration":359,"passed_time":0.9934870911,"remaining_time":1.766199273},
{"learn":[505.2884852],"iteration":360,"passed_time":0.9964158634,"remaining_time":1.763738883},
{"learn":[504.9992],"iteration":361,"passed_time":0.9989976381,"remaining_time":1.760664346},
{"learn":[504.805396],"iteration":362,"passed_time":1.001286248,"remaining_time":1.757078071},
{"learn":[504.5754218],"iteration":363,"passed_time":1.003821398,"remaining_time":1.753929695},
{"learn":[504.4851721],"iteration":364,"passed_time":1.006524338,"remaining_time":1.751076588},
{"learn":[504.3578742],"iteration":365,"passed_time":1.00915932,"remaining_time":1.748106582},
{"learn":[504.1642033],"iteration":366,"passed_time":1.011664428,"remaining_time":1.744914395},
{"learn":[503.8186237],"iteration":367,"passed_time":1.014222869,"remaining_time":1.741817536},
{"learn":[503.3757096],"iteration":368,"passed_time":1.016826435,"remaining_time":1.73880076},
{"learn":[503.1278526],"iteration":369,"passed_time":1.019212419,"remaining_time":1.73541574},
{"learn":[502.9198475],"iteration":370,"passed_time":1.022036775,"remaining_time":1.73277933},
{"learn":[502.7677598],"iteration":371,"passed_time":1.024924671,"remaining_time":1.730249177},
{"learn":[502.648029],"iteration":372,"passed_time":1.027586321,"remaining_time":1.727336791},
{"learn":[502.3034027],"iteration":373,"passed_time":1.030426385,"remaining_time":1.724724376},
{"learn":[502.0396371],"iteration":374,"passed_time":1.03296566,"remaining_time":1.721609433},
{"learn":[501.8804534],"iteration":375,"passed_time":1.035222103,"remaining_time":1.718028172},
{"learn":[501.7469851],"iteration":376,"passed_time":1.037709421,"remaining_time":1.714835462},
{"learn":[501.6162423],"iteration":377,"passed_time":1.040384695,"remaining_time":1.711955768},
{"learn":[501.3690074],"iteration":378,"passed_time":1.043160551,"remaining_time":1.709241959},
{"learn":[501.3264294],"iteration":379,"passed_time":1.045693368,"remaining_time":1.706131285},
{"learn":[501.1713692],"iteration":380,"passed_time":1.048242726,"remaining_time":1.703050519},
{"learn":[501.0218761],"iteration":381,"passed_time":1.050642293,"remaining_time":1.699730202},
{"learn":[500.8268973],"iteration":382,"passed_time":1.053247151,"remaining_time":1.69674541},
{"learn":[500.5797892],"iteration":383,"passed_time":1.055882758,"remaining_time":1.693811924},
{"learn":[500.4436606],"iteration":384,"passed_time":1.0583117,"remaining_time":1.690549858},
{"learn":[500.3888006],"iteration":385,"passed_time":1.06091814,"remaining_time":1.687574451},
{"learn":[500.2180392],"iteration":386,"passed_time":1.063988995,"remaining_time":1.685336573},
{"learn":[500.1391169],"iteration":387,"passed_time":1.066390145,"remaining_time":1.682038063},
{"learn":[500.0033359],"iteration":388,"passed_time":1.069317667,"remaining_time":1.679570937},
{"learn":[499.7605208],"iteration":389,"passed_time":1.071790276,"remaining_time":1.676389918},
{"learn":[499.5884168],"iteration":390,"passed_time":1.075044796,"remaining_time":1.674430385},
{"learn":[499.4056999],"iteration":391,"passed_time":1.077767028,"remaining_time":1.671638655},
{"learn":[499.25797],"iteration":392,"passed_time":1.080392969,"remaining_time":1.668698555},
{"learn":[499.0081306],"iteration":393,"passed_time":1.083040701,"remaining_time":1.665793566},
{"learn":[498.7853289],"iteration":394,"passed_time":1.085512268,"remaining_time":1.662620055},
{"learn":[498.5802861],"iteration":395,"passed_time":1.088118375,"remaining_time":1.659655299},
{"learn":[498.3797329],"iteration":396,"passed_time":1.090777482,"remaining_time":1.656772851},
{"learn":[498.1145623],"iteration":397,"passed_time":1.093207632,"remaining_time":1.653545212},
{"learn":[497.9390849],"iteration":398,"passed_time":1.095602449,"remaining_time":1.650268351},
{"learn":[497.757886],"iteration":399,"passed_time":1.098246306,"remaining_time":1.647369459},
{"learn":[497.6079701],"iteration":400,"passed_time":1.100646831,"remaining_time":1.644108359},
{"learn":[497.4120035],"iteration":401,"passed_time":1.103177189,"remaining_time":1.641044675},
{"learn":[497.312837],"iteration":402,"passed_time":1.105819505,"remaining_time":1.638149489},
{"learn":[497.1089151],"iteration":403,"passed_time":1.108429904,"remaining_time":1.635208472},
{"learn":[496.9770865],"iteration":404,"passed_time":1.110958012,"remaining_time":1.632148191},
{"learn":[496.7417562],"iteration":405,"passed_time":1.113619661,"remaining_time":1.629285908},
{"learn":[496.5290325],"iteration":406,"passed_time":1.116094895,"remaining_time":1.626153004},
{"learn":[496.4099554],"iteration":407,"passed_time":1.118526378,"remaining_time":1.622959843},
{"learn":[496.0727827],"iteration":408,"passed_time":1.12118832,"remaining_time":1.620103415},
{"learn":[495.8887542],"iteration":409,"passed_time":1.123743803,"remaining_time":1.61709474},
{"learn":[495.7643902],"iteration":410,"passed_time":1.126275161,"remaining_time":1.614053697},
{"learn":[495.5675258],"iteration":411,"passed_time":1.129111558,"remaining_time":1.611450475},
{"learn":[495.4216882],"iteration":412,"passed_time":1.132074038,"remaining_time":1.609025327},
{"learn":[495.1973241],"iteration":413,"passed_time":1.134753228,"remaining_time":1.606196598},
{"learn":[494.9750524],"iteration":414,"passed_time":1.137396002,"remaining_time":1.603317256},
{"learn":[494.6763665],"iteration":415,"passed_time":1.140071526,"remaining_time":1.600485027},
{"learn":[494.4767885],"iteration":416,"passed_time":1.142859174,"remaining_time":1.597810309},
{"learn":[494.3972883],"iteration":417,"passed_time":1.145493657,"remaining_time":1.59492179},
{"learn":[494.2650985],"iteration":418,"passed_time":1.148036599,"remaining_time":1.591907551},
{"learn":[494.0320082],"iteration":419,"passed_time":1.151258035,"remaining_time":1.589832525},
{"learn":[493.7413731],"iteration":420,"passed_time":1.153663227,"remaining_time":1.586629474},
{"learn":[493.6148826],"iteration":421,"passed_time":1.156224418,"remaining_time":1.583643871},
{"learn":[493.4671662],"iteration":422,"passed_time":1.158737151,"remaining_time":1.580594175},
{"learn":[493.3338063],"iteration":423,"passed_time":1.161413966,"remaining_time":1.577769916},
{"learn":[493.159298],"iteration":424,"passed_time":1.164032032,"remaining_time":1.574866866},
{"learn":[493.1258978],"iteration":425,"passed_time":1.166607556,"remaining_time":1.571907834},
{"learn":[492.9262997],"iteration":426,"passed_time":1.169318246,"remaining_time":1.569131979},
{"learn":[492.6992133],"iteration":427,"passed_time":1.171967021,"remaining_time":1.566273682},
{"learn":[492.5765646],"iteration":428,"passed_time":1.174763127,"remaining_time":1.56361246},
{"learn":[492.4122379],"iteration":429,"passed_time":1.177621983,"remaining_time":1.561033791},
{"learn":[492.2607063],"iteration":430,"passed_time":1.179919884,"remaining_time":1.557713258},
{"learn":[492.0679602],"iteration":431,"passed_time":1.182359868,"remaining_time":1.554584271},
{"learn":[491.9155093],"iteration":432,"passed_time":1.184913976,"remaining_time":1.551607908},
{"learn":[491.6859048],"iteration":433,"passed_time":1.187545958,"remaining_time":1.548735051},
{"learn":[491.4814159],"iteration":434,"passed_time":1.190142066,"remaining_time":1.545816706},
{"learn":[491.2227652],"iteration":435,"passed_time":1.192798548,"remaining_time":1.542977938},
{"learn":[491.0118662],"iteration":436,"passed_time":1.195352864,"remaining_time":1.540008381},
{"learn":[490.9202868],"iteration":437,"passed_time":1.197885931,"remaining_time":1.537013455},
{"learn":[490.8828233],"iteration":438,"passed_time":1.200331123,"remaining_time":1.533908337},
{"learn":[490.6200167],"iteration":439,"passed_time":1.203349394,"remaining_time":1.531535593},
{"learn":[490.3945287],"iteration":440,"passed_time":1.20587621,"remaining_time":1.528536965},
{"learn":[490.3477483],"iteration":441,"passed_time":1.208539985,"remaining_time":1.525713374},
{"learn":[490.060754],"iteration":442,"passed_time":1.211358091,"remaining_time":1.523084552},
{"learn":[489.9113472],"iteration":443,"passed_time":1.213847574,"remaining_time":1.520043358},
{"learn":[489.7831743],"iteration":444,"passed_time":1.216665722,"remaining_time":1.517414552},
{"learn":[489.6223231],"iteration":445,"passed_time":1.21934637,"remaining_time":1.514614101},
{"learn":[489.4095524],"iteration":446,"passed_time":1.22187352,"remaining_time":1.511624288},
{"learn":[489.2866758],"iteration":447,"passed_time":1.224273379,"remaining_time":1.508479699},
{"learn":[489.1593517],"iteration":448,"passed_time":1.226941152,"remaining_time":1.505667205},
{"learn":[488.9255711],"iteration":449,"passed_time":1.230054548,"remaining_time":1.503400004},
{"learn":[488.7962899],"iteration":450,"passed_time":1.232814239,"remaining_time":1.500698486},
{"learn":[488.6010632],"iteration":451,"passed_time":1.238789699,"remaining_time":1.501895476},
{"learn":[488.4541375],"iteration":452,"passed_time":1.242364967,"remaining_time":1.500162554},
{"learn":[488.1984168],"iteration":453,"passed_time":1.247189851,"remaining_time":1.499924358},
{"learn":[488.0215761],"iteration":454,"passed_time":1.249956957,"remaining_time":1.49720119},
{"learn":[487.920911],"iteration":455,"passed_time":1.252735522,"remaining_time":1.4944915},
{"learn":[487.8740484],"iteration":456,"passed_time":1.255144006,"remaining_time":1.491341784},
{"learn":[487.7317099],"iteration":457,"passed_time":1.257915488,"remaining_time":1.488624879},
{"learn":[487.5955113],"iteration":458,"passed_time":1.260543762,"remaining_time":1.485738944},
{"learn":[487.506597],"iteration":459,"passed_time":1.262877788,"remaining_time":1.482508707},
{"learn":[487.4636688],"iteration":460,"passed_time":1.265375229,"remaining_time":1.479473424},
{"learn":[487.3602417],"iteration":461,"passed_time":1.267785296,"remaining_time":1.476338721},
{"learn":[487.2599754],"iteration":462,"passed_time":1.270637361,"remaining_time":1.47371979},
{"learn":[487.0918353],"iteration":463,"passed_time":1.273248718,"remaining_time":1.470821795},
{"learn":[486.8907879],"iteration":464,"passed_time":1.275824993,"remaining_time":1.467884669},
{"learn":[486.7113568],"iteration":465,"passed_time":1.278281435,"remaining_time":1.464811774},
{"learn":[486.4987495],"iteration":466,"passed_time":1.280704961,"remaining_time":1.461703949},
{"learn":[486.3834574],"iteration":467,"passed_time":1.283389443,"remaining_time":1.458895692},
{"learn":[486.3558453],"iteration":468,"passed_time":1.285741594,"remaining_time":1.455711699},
{"learn":[486.1619719],"iteration":469,"passed_time":1.288187619,"remaining_time":1.452637102},
{"learn":[486.0661715],"iteration":470,"passed_time":1.29200376,"remaining_time":1.451104011},
{"learn":[485.897536],"iteration":471,"passed_time":1.295616111,"remaining_time":1.449333277},
{"learn":[485.7738685],"iteration":472,"passed_time":1.29840651,"remaining_time":1.446638965},
{"learn":[485.5397703],"iteration":473,"passed_time":1.301778154,"remaining_time":1.444589259},
{"learn":[485.4103941],"iteration":474,"passed_time":1.305167047,"remaining_time":1.442553052},
{"learn":[485.3350162],"iteration":475,"passed_time":1.307504241,"remaining_time":1.439353408},
{"learn":[485.2751186],"iteration":476,"passed_time":1.310049016,"remaining_time":1.436384979},
{"learn":[485.107367],"iteration":477,"passed_time":1.312993746,"remaining_time":1.433855095},
{"learn":[484.9983604],"iteration":478,"passed_time":1.315583437,"remaining_time":1.430937309},
{"learn":[484.9572232],"iteration":479,"passed_time":1.318249712,"remaining_time":1.428103854},
{"learn":[484.9309393],"iteration":480,"passed_time":1.320751695,"remaining_time":1.425093825},
{"learn":[484.7738441],"iteration":481,"passed_time":1.323784633,"remaining_time":1.422656514},
{"learn":[484.6054165],"iteration":482,"passed_time":1.326318658,"remaining_time":1.419682704},
{"learn":[484.4717212],"iteration":483,"passed_time":1.329025014,"remaining_time":1.416894437},
{"learn":[484.3809706],"iteration":484,"passed_time":1.331399291,"remaining_time":1.413753886},
{"learn":[484.2284424],"iteration":485,"passed_time":1.333759484,"remaining_time":1.410601594},
{"learn":[484.1464478],"iteration":486,"passed_time":1.336604673,"remaining_time":1.407963444},
{"learn":[483.9969846],"iteration":487,"passed_time":1.339316862,"remaining_time":1.405184905},
{"learn":[483.9426505],"iteration":488,"passed_time":1.341830846,"remaining_time":1.402199514},
{"learn":[483.7547306],"iteration":489,"passed_time":1.344494161,"remaining_time":1.399371474},
{"learn":[483.4756462],"iteration":490,"passed_time":1.346971644,"remaining_time":1.39635146},
{"learn":[483.3516174],"iteration":491,"passed_time":1.349618793,"remaining_time":1.393508836},
{"learn":[483.1062682],"iteration":492,"passed_time":1.352099652,"remaining_time":1.390495991},
{"learn":[482.9361587],"iteration":493,"passed_time":1.354678343,"remaining_time":1.387585509},
{"learn":[482.7474543],"iteration":494,"passed_time":1.357584281,"remaining_time":1.385010226},
{"learn":[482.5977743],"iteration":495,"passed_time":1.36028768,"remaining_time":1.382227804},
{"learn":[482.3734533],"iteration":496,"passed_time":1.362967537,"remaining_time":1.379421874},
{"learn":[482.1530674],"iteration":497,"passed_time":1.365459312,"remaining_time":1.376426857},
{"learn":[481.9721652],"iteration":498,"passed_time":1.368064211,"remaining_time":1.373547434},
{"learn":[481.8517514],"iteration":499,"passed_time":1.370820984,"remaining_time":1.370820984},
{"learn":[481.7147765],"iteration":500,"passed_time":1.373550841,"remaining_time":1.368067604},
{"learn":[481.4234313],"iteration":501,"passed_time":1.375988283,"remaining_time":1.365024233},
{"learn":[481.3956778],"iteration":502,"passed_time":1.378578557,"remaining_time":1.362134279},
{"learn":[481.3012823],"iteration":503,"passed_time":1.38125333,"remaining_time":1.359328674},
{"learn":[481.1452879],"iteration":504,"passed_time":1.383623314,"remaining_time":1.356224832},
{"learn":[481.0730476],"iteration":505,"passed_time":1.38614838,"remaining_time":1.353275296},
{"learn":[480.9451917],"iteration":506,"passed_time":1.388550072,"remaining_time":1.350207466},
{"learn":[480.8005104],"iteration":507,"passed_time":1.39107668,"remaining_time":1.347263241},
{"learn":[480.5457125],"iteration":508,"passed_time":1.393600788,"remaining_time":1.344318245},
{"learn":[480.5243103],"iteration":509,"passed_time":1.396171813,"remaining_time":1.341419977},
{"learn":[480.3769352],"iteration":510,"passed_time":1.398889835,"remaining_time":1.338663659},
{"learn":[480.2790318],"iteration":511,"passed_time":1.401386569,"remaining_time":1.335696573},
{"learn":[480.1211492],"iteration":512,"passed_time":1.40390451,"remaining_time":1.332751455},
{"learn":[480.0235803],"iteration":513,"passed_time":1.406795781,"remaining_time":1.330160992},
{"learn":[479.8741113],"iteration":514,"passed_time":1.409426305,"remaining_time":1.327323802},
{"learn":[479.7040619],"iteration":515,"passed_time":1.41189908,"remaining_time":1.324339447},
{"learn":[479.5950591],"iteration":516,"passed_time":1.414477272,"remaining_time":1.321455556},
{"learn":[479.4253232],"iteration":517,"passed_time":1.416908464,"remaining_time":1.318436061},
{"learn":[479.2990068],"iteration":518,"passed_time":1.41938978,"remaining_time":1.315465288},
{"learn":[479.1824694],"iteration":519,"passed_time":1.422103303,"remaining_time":1.312710741},
{"learn":[478.8975608],"iteration":520,"passed_time":1.425250448,"remaining_time":1.310355018},
{"learn":[478.6665956],"iteration":521,"passed_time":1.428027388,"remaining_time":1.307657264},
{"learn":[478.3901582],"iteration":522,"passed_time":1.430667954,"remaining_time":1.304834826},
{"learn":[478.2256923],"iteration":523,"passed_time":1.433299769,"remaining_time":1.302005134},
{"learn":[478.0455022],"iteration":524,"passed_time":1.435851877,"remaining_time":1.299104079},
{"learn":[477.8828967],"iteration":525,"passed_time":1.438637566,"remaining_time":1.296414841},
{"learn":[477.7420746],"iteration":526,"passed_time":1.441260091,"remaining_time":1.293578791},
{"learn":[477.591982],"iteration":527,"passed_time":1.443723658,"remaining_time":1.290601452},
{"learn":[477.3939829],"iteration":528,"passed_time":1.446312516,"remaining_time":1.287737609},
{"learn":[477.2800982],"iteration":529,"passed_time":1.449113164,"remaining_time":1.285062617},
{"learn":[477.1172292],"iteration":530,"passed_time":1.452056602,"remaining_time":1.28251327},
{"learn":[476.9197259],"iteration":531,"passed_time":1.454426752,"remaining_time":1.279458121},
{"learn":[476.7580651],"iteration":532,"passed_time":1.456903778,"remaining_time":1.276499182},
{"learn":[476.630921],"iteration":533,"passed_time":1.459517344,"remaining_time":1.273661203},
{"learn":[476.4227257],"iteration":534,"passed_time":1.461974745,"remaining_time":1.27068833},
{"learn":[476.1851473],"iteration":535,"passed_time":1.464515561,"remaining_time":1.26778959},
{"learn":[476.1533468],"iteration":536,"passed_time":1.467214501,"remaining_time":1.265028517},
{"learn":[476.0375256],"iteration":537,"passed_time":1.469581943,"remaining_time":1.261983007},
{"learn":[475.9111574],"iteration":538,"passed_time":1.472264508,"remaining_time":1.259209533},
{"learn":[475.8841653],"iteration":539,"passed_time":1.474752407,"remaining_time":1.256270569},
{"learn":[475.7243428],"iteration":540,"passed_time":1.477419514,"remaining_time":1.253485318},
{"learn":[475.6759714],"iteration":541,"passed_time":1.479737999,"remaining_time":1.25040591},
{"learn":[475.5923305],"iteration":542,"passed_time":1.482384814,"remaining_time":1.247605635},
{"learn":[475.324551],"iteration":543,"passed_time":1.485149838,"remaining_time":1.244905011},
{"learn":[475.1497605],"iteration":544,"passed_time":1.487766153,"remaining_time":1.242079999},
{"learn":[475.0083788],"iteration":545,"passed_time":1.490465844,"remaining_time":1.239325079},
{"learn":[474.8295062],"iteration":546,"passed_time":1.492867703,"remaining_time":1.23632371},
{"learn":[474.6618094],"iteration":547,"passed_time":1.495534102,"remaining_time":1.233542727},
{"learn":[474.5516877],"iteration":548,"passed_time":1.49785717,"remaining_time":1.230480116},
{"learn":[474.4652074],"iteration":549,"passed_time":1.500326028,"remaining_time":1.227539477},
{"learn":[474.3639041],"iteration":550,"passed_time":1.50268472,"remaining_time":1.224510779},
{"learn":[474.185771],"iteration":551,"passed_time":1.505403785,"remaining_time":1.221776985},
{"learn":[474.1559675],"iteration":552,"passed_time":1.507984685,"remaining_time":1.218931562},
{"learn":[474.0324777],"iteration":553,"passed_time":1.510605917,"remaining_time":1.216119565},
{"learn":[473.8099862],"iteration":554,"passed_time":1.513038235,"remaining_time":1.213156783},
{"learn":[473.7731761],"iteration":555,"passed_time":1.51541626,"remaining_time":1.210152553},
{"learn":[473.6685498],"iteration":556,"passed_time":1.518184699,"remaining_time":1.20746108},
{"learn":[473.5277971],"iteration":557,"passed_time":1.520858889,"remaining_time":1.204694676},
{"learn":[473.5030022],"iteration":558,"passed_time":1.523318581,"remaining_time":1.201759381},
{"learn":[473.4008477],"iteration":559,"passed_time":1.525663898,"remaining_time":1.19873592},
{"learn":[473.3043506],"iteration":560,"passed_time":1.528173423,"remaining_time":1.195843374},
{"learn":[473.2109538],"iteration":561,"passed_time":1.530646949,"remaining_time":1.192924135},
{"learn":[473.1443539],"iteration":562,"passed_time":1.533304181,"remaining_time":1.190149071},
{"learn":[472.9652893],"iteration":563,"passed_time":1.535592916,"remaining_time":1.187089559},
{"learn":[472.8702847],"iteration":564,"passed_time":1.53829669,"remaining_time":1.184352319},
{"learn":[472.7181647],"iteration":565,"passed_time":1.540902797,"remaining_time":1.181540307},
{"learn":[472.7014996],"iteration":566,"passed_time":1.543466655,"remaining_time":1.178696758},
{"learn":[472.6636428],"iteration":567,"passed_time":1.545932555,"remaining_time":1.17577969},
{"learn":[472.5887524],"iteration":568,"passed_time":1.548573538,"remaining_time":1.172996827},
{"learn":[472.4829851],"iteration":569,"passed_time":1.551110479,"remaining_time":1.170135975},
{"learn":[472.3230805],"iteration":570,"passed_time":1.553812461,"remaining_time":1.167400255},
{"learn":[472.1944557],"iteration":571,"passed_time":1.556403568,"remaining_time":1.164581691},
{"learn":[472.0611937],"iteration":572,"passed_time":1.558766303,"remaining_time":1.161593737},
{"learn":[471.988838],"iteration":573,"passed_time":1.561583868,"remaining_time":1.158945518},
{"learn":[471.8224904],"iteration":574,"passed_time":1.564310099,"remaining_time":1.156229204},
{"learn":[471.7145099],"iteration":575,"passed_time":1.566984373,"remaining_time":1.153474608},
{"learn":[471.557099],"iteration":576,"passed_time":1.569617439,"remaining_time":1.150690081},
{"learn":[471.4169777],"iteration":577,"passed_time":1.572026298,"remaining_time":1.147742383},
{"learn":[471.2421766],"iteration":578,"passed_time":1.574705196,"remaining_time":1.144992897},
{"learn":[471.1484052],"iteration":579,"passed_time":1.577613093,"remaining_time":1.142409481},
{"learn":[470.9901951],"iteration":580,"passed_time":1.580018202,"remaining_time":1.139462352},
{"learn":[470.904519],"iteration":581,"passed_time":1.582852891,"remaining_time":1.136825616},
{"learn":[470.7453863],"iteration":582,"passed_time":1.585463666,"remaining_time":1.134028042},
{"learn":[470.7054771],"iteration":583,"passed_time":1.587959482,"remaining_time":1.13114922},
{"learn":[470.6758858],"iteration":584,"passed_time":1.590170426,"remaining_time":1.128069619},
{"learn":[470.6295158],"iteration":585,"passed_time":1.592816658,"remaining_time":1.125300506},
{"learn":[470.5777784],"iteration":586,"passed_time":1.59524085,"remaining_time":1.12237559},
{"learn":[470.5041897],"iteration":587,"passed_time":1.598116622,"remaining_time":1.11976879},
{"learn":[470.4013046],"iteration":588,"passed_time":1.600641855,"remaining_time":1.116916473},
{"learn":[470.3188336],"iteration":589,"passed_time":1.603110463,"remaining_time":1.114025915},
{"learn":[470.1988061],"iteration":590,"passed_time":1.605912279,"remaining_time":1.111367381},
{"learn":[470.0723372],"iteration":591,"passed_time":1.608636801,"remaining_time":1.108655093},
{"learn":[469.9084546],"iteration":592,"passed_time":1.611254075,"remaining_time":1.105869154},
{"learn":[469.8609274],"iteration":593,"passed_time":1.613901015,"remaining_time":1.103104061},
{"learn":[469.772582],"iteration":594,"passed_time":1.616562164,"remaining_time":1.100349036},
{"learn":[469.7444332],"iteration":595,"passed_time":1.619015939,"remaining_time":1.097453757},
{"learn":[469.5791093],"iteration":596,"passed_time":1.621534463,"remaining_time":1.094603666},
{"learn":[469.5409283],"iteration":597,"passed_time":1.624074946,"remaining_time":1.091769445},
{"learn":[469.4176097],"iteration":598,"passed_time":1.626376639,"remaining_time":1.088776347},
{"learn":[469.1871027],"iteration":599,"passed_time":1.62919812,"remaining_time":1.08613208},
{"learn":[468.9881235],"iteration":600,"passed_time":1.631748936,"remaining_time":1.08330753},
{"learn":[468.9291329],"iteration":601,"passed_time":1.634211919,"remaining_time":1.08042582},
{"learn":[468.8699481],"iteration":602,"passed_time":1.63679561,"remaining_time":1.07762497},
{"learn":[468.638492],"iteration":603,"passed_time":1.639513134,"remaining_time":1.074912584},
{"learn":[468.5635553],"iteration":604,"passed_time":1.642041826,"remaining_time":1.072076894},
{"learn":[468.4957191],"iteration":605,"passed_time":1.644676391,"remaining_time":1.069311053},
{"learn":[468.3718264],"iteration":606,"passed_time":1.647294248,"remaining_time":1.066534826},
{"learn":[468.2359081],"iteration":607,"passed_time":1.650015855,"remaining_time":1.063826012},
{"learn":[468.0110439],"iteration":608,"passed_time":1.652830419,"remaining_time":1.061176837},
{"learn":[467.9208017],"iteration":609,"passed_time":1.655262028,"remaining_time":1.05828228},
{"learn":[467.8640719],"iteration":610,"passed_time":1.657707012,"remaining_time":1.055397754},
{"learn":[467.7735375],"iteration":611,"passed_time":1.660105788,"remaining_time":1.052485369},
{"learn":[467.6723801],"iteration":612,"passed_time":1.662697062,"remaining_time":1.049696188},
{"learn":[467.6021555],"iteration":613,"passed_time":1.665468544,"remaining_time":1.047020941},
{"learn":[467.4322631],"iteration":614,"passed_time":1.667955736,"remaining_time":1.044167412},
{"learn":[467.3865018],"iteration":615,"passed_time":1.670569511,"remaining_time":1.041393981},
{"learn":[467.3186582],"iteration":616,"passed_time":1.673418241,"remaining_time":1.038766915},
{"learn":[467.2400707],"iteration":617,"passed_time":1.676294139,"remaining_time":1.036155924},
{"learn":[467.1079949],"iteration":618,"passed_time":1.679158286,"remaining_time":1.033536845},
{"learn":[467.0072122],"iteration":619,"passed_time":1.681682435,"remaining_time":1.030708589},
{"learn":[466.9306825],"iteration":620,"passed_time":1.68428321,"remaining_time":1.027928078},
{"learn":[466.9213021],"iteration":621,"passed_time":1.686629569,"remaining_time":1.024993532},
{"learn":[466.8097451],"iteration":622,"passed_time":1.689352009,"remaining_time":1.022288455},
{"learn":[466.6691292],"iteration":623,"passed_time":1.691852033,"remaining_time":1.019449302},
{"learn":[466.5914822],"iteration":624,"passed_time":1.694545932,"remaining_time":1.016727559},
{"learn":[466.5113072],"iteration":625,"passed_time":1.697006415,"remaining_time":1.013866453},
{"learn":[466.356003],"iteration":626,"passed_time":1.699528774,"remaining_time":1.011043433},
{"learn":[466.2521583],"iteration":627,"passed_time":1.702166339,"remaining_time":1.008289615},
{"learn":[466.2083103],"iteration":628,"passed_time":1.70503932,"remaining_time":1.00567502},
{"learn":[466.2065313],"iteration":629,"passed_time":1.707291555,"remaining_time":1.00269504},
{"learn":[466.1107409],"iteration":630,"passed_time":1.710021703,"remaining_time":0.9999968439},
{"learn":[465.9570119],"iteration":631,"passed_time":1.71269006,"remaining_time":0.9972625668},
{"learn":[465.8119952],"iteration":632,"passed_time":1.715001628,"remaining_time":0.994321639},
{"learn":[465.7268573],"iteration":633,"passed_time":1.717674818,"remaining_time":0.9915914565},
{"learn":[465.7251579],"iteration":634,"passed_time":1.720372134,"remaining_time":0.9888753211},
{"learn":[465.5792901],"iteration":635,"passed_time":1.722771493,"remaining_time":0.9859887161},
{"learn":[465.4680085],"iteration":636,"passed_time":1.725554974,"remaining_time":0.9833225364},
{"learn":[465.4506382],"iteration":637,"passed_time":1.728069332,"remaining_time":0.9805032889},
{"learn":[465.2566536],"iteration":638,"passed_time":1.730619065,"remaining_time":0.9777049806},
{"learn":[465.091918],"iteration":639,"passed_time":1.733343505,"remaining_time":0.9750057216},
{"learn":[464.9293988],"iteration":640,"passed_time":1.735750239,"remaining_time":0.972128449},
{"learn":[464.9279946],"iteration":641,"passed_time":1.738027891,"remaining_time":0.9691806618},
{"learn":[464.8283488],"iteration":642,"passed_time":1.741046912,"remaining_time":0.966646575},
{"learn":[464.67171],"iteration":643,"passed_time":1.743608311,"remaining_time":0.9638580106},
{"learn":[464.5702743],"iteration":644,"passed_time":1.746154503,"remaining_time":0.9610617809},
{"learn":[464.5689211],"iteration":645,"passed_time":1.748823902,"remaining_time":0.9583338412},
{"learn":[464.5054831],"iteration":646,"passed_time":1.751502343,"remaining_time":0.9556110158},
{"learn":[464.5039272],"iteration":647,"passed_time":1.753799036,"remaining_time":0.9526809579},
{"learn":[464.5024202],"iteration":648,"passed_time":1.756070104,"remaining_time":0.949738993},
{"learn":[464.3988113],"iteration":649,"passed_time":1.758621212,"remaining_time":0.9469498833},
{"learn":[464.3086558],"iteration":650,"passed_time":1.761409235,"remaining_time":0.9442885147},
{"learn":[464.2074896],"iteration":651,"passed_time":1.763938801,"remaining_time":0.941488808},
{"learn":[464.1455615],"iteration":652,"passed_time":1.766718658,"remaining_time":0.9388229313},
{"learn":[464.1052243],"iteration":653,"passed_time":1.769322723,"remaining_time":0.9360637036},
{"learn":[464.0406387],"iteration":654,"passed_time":1.771766457,"remaining_time":0.9332205001},
{"learn":[463.8941719],"iteration":655,"passed_time":1.77452498,"remaining_time":0.9305435872},
{"learn":[463.8582438],"iteration":656,"passed_time":1.777073713,"remaining_time":0.9277569005},
{"learn":[463.7168394],"iteration":657,"passed_time":1.779486738,"remaining_time":0.9249004018},
{"learn":[463.5707355],"iteration":658,"passed_time":1.781873264,"remaining_time":0.9220315372},
{"learn":[463.4047752],"iteration":659,"passed_time":1.784567163,"remaining_time":0.9193224779},
{"learn":[463.4034153],"iteration":660,"passed_time":1.787084437,"remaining_time":0.9165228808},
{"learn":[463.2731325],"iteration":661,"passed_time":1.789924793,"remaining_time":0.9138890937},
{"learn":[463.2399246],"iteration":662,"passed_time":1.792432109,"remaining_time":0.9110854009},
{"learn":[463.056065],"iteration":663,"passed_time":1.795041467,"remaining_time":0.9083342362},
{"learn":[462.9501124],"iteration":664,"passed_time":1.797675324,"remaining_time":0.90559584},
{"learn":[462.7576987],"iteration":665,"passed_time":1.800327306,"remaining_time":0.9028668473},
{"learn":[462.7002432],"iteration":666,"passed_time":1.803205745,"remaining_time":0.9002511441},
{"learn":[462.4773813],"iteration":667,"passed_time":1.805903186,"remaining_time":0.8975446973},
{"learn":[462.4186626],"iteration":668,"passed_time":1.808277254,"remaining_time":0.8946782827},
{"learn":[462.330947],"iteration":669,"passed_time":1.810988069,"remaining_time":0.8919791982},
{"learn":[462.2815231],"iteration":670,"passed_time":1.813855883,"remaining_time":0.8893570573},
{"learn":[462.2185408],"iteration":671,"passed_time":1.816497823,"remaining_time":0.8866239375},
{"learn":[462.1393981],"iteration":672,"passed_time":1.819081472,"remaining_time":0.8838627656},
{"learn":[462.0165293],"iteration":673,"passed_time":1.821883119,"remaining_time":0.881207562},
{"learn":[461.9389744],"iteration":674,"passed_time":1.824252394,"remaining_time":0.8783437453},
{"learn":[461.8541715],"iteration":675,"passed_time":1.826995459,"remaining_time":0.8756605453},
{"learn":[461.8528238],"iteration":676,"passed_time":1.829292193,"remaining_time":0.8727642222},
{"learn":[461.7748259],"iteration":677,"passed_time":1.832007009,"remaining_time":0.8700682256},
{"learn":[461.7661646],"iteration":678,"passed_time":1.834443618,"remaining_time":0.86724065},
{"learn":[461.6143015],"iteration":679,"passed_time":1.836997768,"remaining_time":0.8644695378},
{"learn":[461.4482964],"iteration":680,"passed_time":1.839902082,"remaining_time":0.8618630899},
{"learn":[461.3043438],"iteration":681,"passed_time":1.842636981,"remaining_time":0.8591767741},
{"learn":[461.1689013],"iteration":682,"passed_time":1.845231464,"remaining_time":0.8564251449},
{"learn":[461.1095037],"iteration":683,"passed_time":1.847912321,"remaining_time":0.8537138791},
{"learn":[460.8954322],"iteration":684,"passed_time":1.850423637,"remaining_time":0.8509247381},
{"learn":[460.8104475],"iteration":685,"passed_time":1.853304243,"remaining_time":0.8483054405},
{"learn":[460.7292445],"iteration":686,"passed_time":1.856113307,"remaining_time":0.8456527875},
{"learn":[460.5545146],"iteration":687,"passed_time":1.858842996,"remaining_time":0.8429636844},
{"learn":[460.4214099],"iteration":688,"passed_time":1.861317022,"remaining_time":0.8401590621},
{"learn":[460.2720025],"iteration":689,"passed_time":1.86398592,"remaining_time":0.8374429496},
{"learn":[460.0964287],"iteration":690,"passed_time":1.866691361,"remaining_time":0.8347433148},
{"learn":[459.8996442],"iteration":691,"passed_time":1.869252302,"remaining_time":0.8319793482},
{"learn":[459.809754],"iteration":692,"passed_time":1.871825909,"remaining_time":0.8292215789},
{"learn":[459.7826832],"iteration":693,"passed_time":1.874280935,"remaining_time":0.8264120549},
{"learn":[459.7642265],"iteration":694,"passed_time":1.87652517,"remaining_time":0.8235110458},
{"learn":[459.6112737],"iteration":695,"passed_time":1.879343401,"remaining_time":0.820862635},
{"learn":[459.472457],"iteration":696,"passed_time":1.881942301,"remaining_time":0.818118389},
{"learn":[459.419203],"iteration":697,"passed_time":1.884440242,"remaining_time":0.8153308783},
{"learn":[459.2901392],"iteration":698,"passed_time":1.886950808,"remaining_time":0.8125496327},
{"learn":[459.2888169],"iteration":699,"passed_time":1.889291625,"remaining_time":0.8096964109},
{"learn":[459.2058975],"iteration":700,"passed_time":1.891815109,"remaining_time":0.8069225641},
{"learn":[459.0842691],"iteration":701,"passed_time":1.894505341,"remaining_time":0.8042202158},
{"learn":[458.858438],"iteration":702,"passed_time":1.89731428,"remaining_time":0.8015680527},
{"learn":[458.8255663],"iteration":703,"passed_time":1.900006554,"remaining_time":0.7988663919},
{"learn":[458.7673595],"iteration":704,"passed_time":1.902390288,"remaining_time":0.7960356523},
{"learn":[458.5116536],"iteration":705,"passed_time":1.904807063,"remaining_time":0.7932199382},
{"learn":[458.4910679],"iteration":706,"passed_time":1.907347421,"remaining_time":0.7904565689},
{"learn":[458.437226],"iteration":707,"passed_time":1.909924778,"remaining_time":0.7877090893},
{"learn":[458.1958044],"iteration":708,"passed_time":1.912550844,"remaining_time":0.7849820811},
{"learn":[458.007233],"iteration":709,"passed_time":1.915043952,"remaining_time":0.7822010508},
{"learn":[457.7101945],"iteration":710,"passed_time":1.91759581,"remaining_time":0.7794447103},
{"learn":[457.6570972],"iteration":711,"passed_time":1.920044959,"remaining_time":0.7766473993},
{"learn":[457.5010982],"iteration":712,"passed_time":1.922617901,"remaining_time":0.7739008943},
{"learn":[457.4189819],"iteration":713,"passed_time":1.92530805,"remaining_time":0.771201824},
{"learn":[457.3680544],"iteration":714,"passed_time":1.927843033,"remaining_time":0.7684409293},
{"learn":[457.3602959],"iteration":715,"passed_time":1.930146643,"remaining_time":0.7655888918},
{"learn":[457.2233087],"iteration":716,"passed_time":1.932828584,"remaining_time":0.7628877116},
{"learn":[457.0973603],"iteration":717,"passed_time":1.935323317,"remaining_time":0.7601130577},
{"learn":[457.0596285],"iteration":718,"passed_time":1.937907634,"remaining_time":0.7573741935},
{"learn":[456.9864316],"iteration":719,"passed_time":1.940428117,"remaining_time":0.7546109344},
{"learn":[456.9574497],"iteration":720,"passed_time":1.942814059,"remaining_time":0.7517962863},
{"learn":[456.7702853],"iteration":721,"passed_time":1.94569929,"remaining_time":0.7491750727},
{"learn":[456.7350597],"iteration":722,"passed_time":1.948259731,"remaining_time":0.7464286938},
{"learn":[456.7026876],"iteration":723,"passed_time":1.950718548,"remaining_time":0.7436440874},
{"learn":[456.6200513],"iteration":724,"passed_time":1.95350557,"remaining_time":0.7409848715},
{"learn":[456.6188426],"iteration":725,"passed_time":1.955849555,"remaining_time":0.7381580964},
{"learn":[456.5651764],"iteration":726,"passed_time":1.958545621,"remaining_time":0.7354648616},
{"learn":[456.4643192],"iteration":727,"passed_time":1.961181812,"remaining_time":0.7327492484},
{"learn":[456.4631274],"iteration":728,"passed_time":1.963726045,"remaining_time":0.7299996683},
{"learn":[456.402381],"iteration":729,"passed_time":1.966208112,"remaining_time":0.7272276579},
{"learn":[456.3444396],"iteration":730,"passed_time":1.968863094,"remaining_time":0.7245200717},
{"learn":[456.2812449],"iteration":731,"passed_time":1.971721075,"remaining_time":0.7218869511},
{"learn":[456.1463211],"iteration":732,"passed_time":1.974110309,"remaining_time":0.7190824728},
{"learn":[456.1026039],"iteration":733,"passed_time":1.976509585,"remaining_time":0.7162827652},
{"learn":[455.9531257],"iteration":734,"passed_time":1.979215233,"remaining_time":0.7135946079},
{"learn":[455.787216],"iteration":735,"passed_time":1.981602175,"remaining_time":0.7107920846},
{"learn":[455.7126069],"iteration":736,"passed_time":1.983929951,"remaining_time":0.7079695753},
{"learn":[455.6156943],"iteration":737,"passed_time":1.986594392,"remaining_time":0.7052679277},
{"learn":[455.5847979],"iteration":738,"passed_time":1.989148375,"remaining_time":0.7025273691},
{"learn":[455.4374807],"iteration":739,"passed_time":1.991776482,"remaining_time":0.6998133585},
{"learn":[455.4246867],"iteration":740,"passed_time":1.993982051,"remaining_time":0.696951891},
{"learn":[455.4235387],"iteration":741,"passed_time":1.996261369,"remaining_time":0.6941178345},
{"learn":[455.3794165],"iteration":742,"passed_time":1.999128475,"remaining_time":0.6914885841},
{"learn":[455.246943],"iteration":743,"passed_time":2.001639083,"remaining_time":0.6887360285},
{"learn":[455.2180909],"iteration":744,"passed_time":2.004324523,"remaining_time":0.6860439642},
{"learn":[455.2168502],"iteration":745,"passed_time":2.006721341,"remaining_time":0.6832536469},
{"learn":[455.1542464],"iteration":746,"passed_time":2.009644196,"remaining_time":0.6806425457},
{"learn":[455.1038557],"iteration":747,"passed_time":2.01268726,"remaining_time":0.6780711089},
{"learn":[455.1026589],"iteration":748,"passed,
{"learn":[468.1632665],"iteration":749,"passed,
{"learn":[454.9585132],"iteration":749,"passed_,
{"learn":[468.0075509],"iteration":750,"passed,
{"learn":[454.7355506],"iteration":750,"passed_,
{"learn":[467.877493],"iteration":751,"passed_,
{"learn":[454.7207629],"iteration":751,"passed,
{"learn":[467.8598317],"iteration":752,"passed_,
{"learn":[454.6747076],"iteration":752,"passed,
{"learn":[467.7067266],"iteration":753,"passed,
{"learn":[454.4812236],"iteration":753,"passed_,
{"learn":[467.6497523],"iteration":754,"passe,
{"learn":[454.4544041],"iteration":754,"passed_t,
{"learn":[467.6128022],"iteration":755,"passe,
{"learn":[454.3967657],"iteration":755,"passed_t,
{"learn":[467.5487627],"iteration":756,"passe,
{"learn":[454.3337068],"iteration":756,"passed_t,
{"learn":[467.4704711],"iteration":757,"passe,
{"learn":[454.2156706],"iteration":757,"passed_t,
{"learn":[467.4316505],"iteration":758,"pass,
{"learn":[454.1214573],"iteration":758,"passed_ti,
{"learn":[467.3278037],"iteration":759,"pas,
{"learn":[454.0563451],"iteration":759,"passed_ti,
{"learn":[467.2556356],"iteration":760,"pass,
{"learn":[453.9794838],"iteration":760,"passed_ti,
{"learn":[467.1992514],"iteration":761,"pass,
{"learn":[453.8984584],"iteration":761,"passed_ti,
{"learn":[467.0695029],"iteration":762,"p,
{"learn":[453.8203295],"iteration":762,"passed_time",
{"learn":[467.0117029],"iteration":763,"p,
{"learn":[453.7741653],"iteration":763,"passed_time",
{"learn":[466.9420049],"iteration":764,"p,
{"learn":[453.7459505],"iteration":764,"passed_time",
{"learn":[466.9297138],"iteration":765,,
{"learn":[453.6135921],"iteration":765,"passed_time":,
{"learn":[466.7619866],"iteration":766,,
{"learn":[453.5630553],"iteration":766,"passed_time":2,
{"learn":[466.5524268],"iteration":767,,
{"learn":[453.4562829],"iteration":767,"passed_time":2,
{"learn":[466.4683092],"iteration":768,,
{"learn":[453.3658135],"iteration":768,"passed_time":2,
{"learn":[466.3376139],"iteration":769,,
{"learn":[453.3170246],"iteration":769,"passed_time":,
{"learn":[466.2366722],"iteration":770,",
{"learn":[453.2151479],"iteration":770,"passed_time":,
{"learn":[466.1321566],"iteration":771,",
{"learn":[453.1015457],"iteration":771,"passed_time":,
{"learn":[466.0646261],"iteration":772,",
{"learn":[452.9444937],"iteration":772,"passed_time":,
{"learn":[465.9165112],"iteration":773,",
{"learn":[452.8741492],"iteration":773,"passed_time":,
{"learn":[465.8578573],"iteration":774,",
{"learn":[452.8263615],"iteration":774,"passed_time":,
{"learn":[465.8268131],"iteration":775,",
{"learn":[452.7650356],"iteration":775,"passed_time":,
{"learn":[465.7543925],"iteration":776,",
{"learn":[452.6185836],"iteration":776,"passed_time":,
{"learn":[465.7528951],"iteration":777,",
{"learn":[452.5268376],"iteration":777,"passed_time",
{"learn":[465.7336392],"iteration":778,"p,
{"learn":[452.4959704],"iteration":778,"passed_time",
{"learn":[465.6529024],"iteration":779,"p,
{"learn":[452.4254431],"iteration":779,"passed_time",
{"learn":[465.5097996],"iteration":780,",
{"learn":[452.3971801],"iteration":780,"passed_time":,
{"learn":[465.4996875],"iteration":781,"passed_time":2.124859173,"remaining_time":0.5923520456},
{"learn":[465.3668497],"iteration":782,"passed_time":2.127509792,"remaining_time":0.5896163791},
{"learn":[465.3496196],"iteration":783,",
{"learn":[452.265843],"iteration":783,"passed_time":2,
{"learn":[465.2205143],"iteration":784,
{"learn":[452.2463424],"iteration":784,"passed_time":2,
{"learn":[465.1600454],"iteration":785,,
{"learn":[452.1488627],"iteration":785,"passed_time":2,
{"learn":[465.1354241],"iteration":786,,
{"learn":[452.0555265],"iteration":786,"passed_time":2,
{"learn":[465.0607466],"iteration":787,,
{"learn":[452.0545372],"iteration":787,"passed_time":2,
{"learn":[464.9800608],"iteration":788,,
{"learn":[451.8562164],"iteration":788,"passed_time":2,
{"learn":[464.8202025],"iteration":789,,
{"learn":[451.8166949],"iteration":789,"passed_time":2,
{"learn":[464.6959405],"iteration":790,,
{"learn":[451.8157035],"iteration":790,"passed_time":2,
{"learn":[464.6369157],"iteration":791,,
{"learn":[451.6923126],"iteration":791,"passed_time":2,
{"learn":[464.5413073],"iteration":792,,
{"learn":[451.6279193],"iteration":792,"passed_time":2,
{"learn":[464.491952],"iteration":793,"passed_time":2.156110087,"remaining_time":0.559393801},
{"learn":[464.4855941],"iteration":794,"passed_time":2.158567037,"remaining_time":0.5566116258},
{"learn":[464.3800896],"iteration":795,"passed_time":2.16121303,"remaining_time":0.5538787161},
{"learn":[464.2959995],"iteration":796,"passed_time":2.163559727,"remaining_time":0.5510697924},
{"learn":[464.2156219],"iteration":797,"passed_time":2.166172469,"remaining_time":0.5483293719},
{"learn":[464.2037665],"iteration":798,"passed_time":2.168519084,"remaining_time":0.5455223228},
{"learn":[464.0560604],"iteration":799,"passed_time":2.170875158,"remaining_time":0.5427187894},
{"learn":[463.8643644],"iteration":800,"passed_time":2.173510942,"remaining_time":0.5399858646},
{"learn":[463.7450526],"iteration":801,",
{"learn":[450.7654514],"iteration":801,"passed_time",
{"learn":[463.7288476],"iteration":802,"p,
{"learn":[450.5979987],"iteration":802,"passed_time",
{"learn":[463.5708294],"iteration":803,"p,
{"learn":[450.4633123],"iteration":803,"passed_time",
{"learn":[463.4761467],"iteration":804,"p,
{"learn":[450.4211403],"iteration":804,"passed_time",
{"learn":[463.3736444],"iteration":805,"p,
{"learn":[450.2298358],"iteration":805,"passed_time",
{"learn":[463.2006827],"iteration":806,"p,
{"learn":[450.0841693],"iteration":806,"passed_time",
{"learn":[463.1405541],"iteration":807,"passed_time":2.191188635,"remaining_time":0.5206784876},
{"learn":[463.0916269],"iteration":808,"p,
{"learn":[449.9884901],"iteration":808,"passed_time",
{"learn":[462.949818],"iteration":809,"pa,
{"learn":[449.9698878],"iteration":809,"passed_time,
{"learn":[462.7370945],"iteration":810,"p,
{"learn":[449.7566187],"iteration":810,"passed_time",
{"learn":[462.6309344],"iteration":811,"p,
{"learn":[449.5955362],"iteration":811,"passed_time",
{"learn":[462.6164597],"iteration":812,"p,
{"learn":[449.5944531],"iteration":812,"passed_time",
{"learn":[462.5409423],"iteration":813,"p,
{"learn":[449.4414665],"iteration":813,"passed_time",
{"learn":[462.4770034],"iteration":814,"p,
{"learn":[449.3740698],"iteration":814,"passed_time",
{"learn":[462.3431275],"iteration":815,"p,
{"learn":[449.3224397],"iteration":815,"passed_time",
{"learn":[462.279274],"iteration":816,"passed_time":2.213949102,"remaining_time":0.4959029201},
{"learn":[462.175987],"iteration":817,"passed_time":2.216654138,"remaining_time":0.4931919965},
{"learn":[461.9786237],"iteration":818,"passed_time":2.219211838,"remaining_time":0.4904485259},
{"learn":[461.8877577],"iteration":819,"passed_time":2.22180333,"remaining_time":0.4877129262},
{"learn":[461.778469],"iteration":820,"passed_time":2.224343614,"remaining_time":0.4849665127},
{"learn":[461.5355387],"iteration":821,"passed_time":2.227056734,"remaining_time":0.4822580275},
{"learn":[461.4695897],"iteration":822,"passed_time":2.229755895,"remaining_time":0.479546529},
{"learn":[461.329757],"iteration":823,"passed_time":2.232398638,"remaining_time":0.47682301},
{"learn":[461.1665821],"iteration":824,"passed_time":2.234837795,"remaining_time":0.4740565019},
{"learn":[460.989832],"iteration":825,"passed_time":2.237558456,"remaining_time":0.4713500863},
{"learn":[460.8785692],"iteration":826,"passed_time":2.240258658,"remaining_time":0.4686393564},
{"learn":[460.8502797],"iteration":827,"passed_time":2.24270894,"remaining_time":0.4658767363},
{"learn":[460.7206258],"iteration":828,"passed_time":2.245415309,"remaining_time":0.4631676934},
{"learn":[460.6159387],"iteration":829,"passed_time":2.247941592,"remaining_time":0.4604217719},
{"learn":[460.4967828],"iteration":830,"passed_time":2.250724046,"remaining_time":0.4577284763},
{"learn":[460.287227],"iteration":831,"passed_time":2.253473582,"remaining_time":0.4550283195},
{"learn":[460.1634035],"iteration":832,"passed_time":2.255866947,"remaining_time":0.4522566388},
{"learn":[460.0769817],"iteration":833,"passed_time":2.258375313,"remaining_time":0.4495087554},
{"learn":[459.9888119],"iteration":834,"passed_time":2.26114985,"remaining_time":0.4468140422},
{"learn":[459.9283281],"iteration":835,"passed_time":2.263616717,"remaining_time":0.4440587817},
{"learn":[459.9051924],"iteration":836,"passed_time":2.265899664,"remaining_time":0.4412683933},
{"learn":[459.7995487],"iteration":837,"passed_time":2.268691951,"remaining_time":0.4385776802},
{"learn":[459.7264823],"iteration":838,"passed_time":2.271383194,"remaining_time":0.4358673353},
{"learn":[459.719129],"iteration":839,"passed_time":2.273619182,"remaining_time":0.4330703204},
{"learn":[459.6349721],"iteration":840,"passed_time":2.276422427,"remaining_time":0.4303818857},
{"learn":[459.5109682],"iteration":841,"passed_time":2.279065045,"remaining_time":0.427663037},
{"learn":[459.4586347],"iteration":842,"passed_time":2.281675205,"remaining_time":0.424938324},
{"learn":[459.3213645],"iteration":843,"passed_time":2.284306031,"remaining_time":0.4222177025},
{"learn":[459.2627927],"iteration":844,"passed_time":2.286870106,"remaining_time":0.4194850491},
{"learn":[459.1400276],"iteration":845,"passed_time":2.289673976,"remaining_time":0.4167964449},
{"learn":[459.1161673],"iteration":846,"passed_time":2.292352804,"remaining_time":0.4140849811},
{"learn":[459.0223264],"iteration":847,"passed_time":2.294858003,"remaining_time":0.4113424722},
{"learn":[458.8624778],"iteration":848,"passed_time":2.297623582,"remaining_time":0.4086468325},
{"learn":[458.7323261],"iteration":849,"passed_time":2.300389327,"remaining_time":0.4059510577},
{"learn":[458.6410941],"iteration":850,"passed_time":2.302809401,"remaining_time":0.4031945955},
{"learn":[458.4774865],"iteration":851,"passed_time":2.305500853,"remaining_time":0.4004860636},
{"learn":[458.4545637],"iteration":852,"passed_time":2.308024053,"remaining_time":0.3977485766},
{"learn":[458.4534387],"iteration":853,"passed_time":2.310301583,"remaining_time":0.3949695915},
{"learn":[458.34143],"iteration":854,"passed_time":2.312909618,"remaining_time":0.3922478299},
{"learn":[458.256338],"iteration":855,"passed_time":2.315790447,"remaining_time":0.3895722247},
{"learn":[458.1434594],"iteration":856,"passed_time":2.318128478,"remaining_time":0.3868055687},
{"learn":[458.0294343],"iteration":857,"passed_time":2.321124935,"remaining_time":0.3841488819},
{"learn":[457.9795552],"iteration":858,"passed_time":2.323968597,"remaining_time":0.3814663239},
{"learn":[457.8520245],"iteration":859,"passed_time":2.326613716,"remaining_time":0.3787510701},
{"learn":[457.8328698],"iteration":860,"passed_time":2.329400461,"remaining_time":0.3760588433},
{"learn":[457.8150433],"iteration":861,"passed_time":2.331854701,"remaining_time":0.3733131657},
{"learn":[457.6848458],"iteration":862,"passed_time":2.334628863,"remaining_time":0.3706189505},
{"learn":[457.6421892],"iteration":863,"passed_time":2.337257982,"remaining_time":0.3679017194},
{"learn":[457.5590422],"iteration":864,"passed_time":2.339665639,"remaining_time":0.3651501286},
{"learn":[457.4775944],"iteration":865,"passed_time":2.342410258,"remaining_time":0.3624514718},
{"learn":[457.4150928],"iteration":866,"passed_time":2.345141502,"remaining_time":0.3597506572},
{"learn":[457.3774483],"iteration":867,"passed_time":2.347553909,"remaining_time":0.3570012857},
{"learn":[457.3245179],"iteration":868,"passed_time":2.349881815,"remaining_time":0.3542399514},
{"learn":[457.2795761],"iteration":869,"passed_time":2.352672227,"remaining_time":0.3515487236},
{"learn":[457.1884866],"iteration":870,"passed_time":2.35517526,"remaining_time":0.3488147056},
{"learn":[457.0807935],"iteration":871,"passed_time":2.357922462,"remaining_time":0.3461170587},
{"learn":[457.0262611],"iteration":872,"passed_time":2.360486204,"remaining_time":0.3433926093},
{"learn":[456.8991267],"iteration":873,"passed_time":2.36393325,"remaining_time":0.340795869},
{"learn":[456.8277898],"iteration":874,"passed_time":2.366838538,"remaining_time":0.3381197912},
{"learn":[456.6798122],"iteration":875,"passed_time":2.369253861,"remaining_time":0.3353738343},
{"learn":[456.5666543],"iteration":876,"passed_time":2.372173942,"remaining_time":0.332699424},
{"learn":[456.440054],"iteration":877,"passed_time":2.374724143,"remaining_time":0.3299730586},
{"learn":[456.2764705],"iteration":878,"passed_time":2.37756343,"remaining_time":0.3272868886},
{"learn":[456.2023052],"iteration":879,"passed_time":2.380177715,"remaining_time":0.3245696884},
{"learn":[456.0829694],"iteration":880,"passed_time":2.3828165,"remaining_time":0.3218560312},
{"learn":[456.0249301],"iteration":881,"passed_time":2.385283782,"remaining_time":0.319119599},
{"learn":[455.9590594],"iteration":882,"passed_time":2.387880109,"remaining_time":0.3164008751},
{"learn":[455.8223343],"iteration":883,"passed_time":2.390584936,"remaining_time":0.3136966658},
{"learn":[455.7484668],"iteration":884,"passed_time":2.393392056,"remaining_time":0.3110057474},
{"learn":[455.6862371],"iteration":885,"passed_time":2.396441096,"remaining_time":0.3083456941},
{"learn":[455.667757],"iteration":886,"passed_time":2.39919705,"remaining_time":0.3056474257},
{"learn":[455.4928794],"iteration":887,"passed_time":2.401844918,"remaining_time":0.302935395},
{"learn":[455.3883798],"iteration":888,"passed_time":2.404473243,"remaining_time":0.3002210686},
{"learn":[455.3468979],"iteration":889,"passed_time":2.406921443,"remaining_time":0.2974846727},
{"learn":[455.2252499],"iteration":890,"passed_time":2.409644104,"remaining_time":0.2947824998},
{"learn":[455.0530779],"iteration":891,"passed_time":2.412076178,"remaining_time":0.2920450978},
{"learn":[454.8873529],"iteration":892,"passed_time":2.414585419,"remaining_time":0.2893176258},
{"learn":[454.7239976],"iteration":893,"passed_time":2.417217537,"remaining_time":0.2866052113},
{"learn":[454.58916],"iteration":894,"passed_time":2.419646569,"remaining_time":0.2838691506},
{"learn":[454.4253753],"iteration":895,"passed_time":2.422123727,"remaining_time":0.2811393612},
{"learn":[454.424171],"iteration":896,"passed_time":2.424210462,"remaining_time":0.2783653039},
{"learn":[454.3186183],"iteration":897,"passed_time":2.426835122,"remaining_time":0.275653878},
{"learn":[454.1872054],"iteration":898,"passed_time":2.429965164,"remaining_time":0.2729994233},
{"learn":[454.057329],"iteration":899,"passed_time":2.432410196,"remaining_time":0.2702677996},
{"learn":[453.9498447],"iteration":900,"passed_time":2.434693142,"remaining_time":0.2675190023},
{"learn":[453.8011929],"iteration":901,"passed_time":2.437305011,"remaining_time":0.2648069746},
{"learn":[453.7060719],"iteration":902,"passed_time":2.439869837,"remaining_time":0.2620901153},
{"learn":[453.6737312],"iteration":903,"passed_time":2.442363203,"remaining_time":0.2593660038},
{"learn":[453.5299432],"iteration":904,"passed_time":2.44539491,"remaining_time":0.2566989132},
{"learn":[453.4778848],"iteration":905,"passed_time":2.448198197,"remaining_time":0.2540073184},
{"learn":[453.4566509],"iteration":906,"passed_time":2.450663729,"remaining_time":0.2512808455},
{"learn":[453.3117979],"iteration":907,"passed_time":2.453245389,"remaining_time":0.2485667134},
{"learn":[453.2174556],"iteration":908,"passed_time":2.455980967,"remaining_time":0.2458682816},
{"learn":[453.1635384],"iteration":909,"passed_time":2.45814237,"remaining_time":0.2431129817},
{"learn":[453.090712],"iteration":910,"passed_time":2.46044036,"remaining_time":0.2403723293},
{"learn":[453.0070257],"iteration":911,"passed_time":2.463193854,"remaining_time":0.2376766},
{"learn":[452.9129409],"iteration":912,"passed_time":2.465772305,"remaining_time":0.2349640642},
{"learn":[452.7534196],"iteration":913,"passed_time":2.468545175,"remaining_time":0.2322701149},
{"learn":[452.6397502],"iteration":914,"passed_time":2.471162043,"remaining_time":0.2295615012},
{"learn":[452.583664],"iteration":915,"passed_time":2.47399508,"remaining_time":0.2268729113},
{"learn":[452.5101898],"iteration":916,"passed_time":2.476759033,"remaining_time":0.2241777532},
{"learn":[452.3862428],"iteration":917,"passed_time":2.479471777,"remaining_time":0.2214778711},
{"learn":[452.3202073],"iteration":918,"passed_time":2.482087436,"remaining_time":0.2187694041},
{"learn":[452.1769791],"iteration":919,"passed_time":2.484639928,"remaining_time":0.2160556459},
{"learn":[452.0422045],"iteration":920,"passed_time":2.487338506,"remaining_time":0.2133547687},
{"learn":[451.9756936],"iteration":921,"passed_time":2.490206002,"remaining_time":0.2106681867},
{"learn":[451.9122675],"iteration":922,"passed_time":2.493051956,"remaining_time":0.2079794156},
{"learn":[451.8682142],"iteration":923,"passed_time":2.495752659,"remaining_time":0.2052783572},
{"learn":[451.7177317],"iteration":924,"passed_time":2.498276526,"remaining_time":0.2025629616},
{"learn":[451.6088983],"iteration":925,"passed_time":2.500936978,"remaining_time":0.1998588945},
{"learn":[451.5173904],"iteration":926,"passed_time":2.503751057,"remaining_time":0.1971670196},
{"learn":[451.3121734],"iteration":927,"passed_time":2.50628109,"remaining_time":0.1944528432},
{"learn":[451.2122858],"iteration":928,"passed_time":2.508755998,"remaining_time":0.1917348502},
{"learn":[451.1118202],"iteration":929,"passed_time":2.511561118,"remaining_time":0.1890422347},
{"learn":[451.0318746],"iteration":930,"passed_time":2.51418307,"remaining_time":0.1863358022},
{"learn":[450.9575601],"iteration":931,"passed_time":2.516995941,"remaining_time":0.1836434807},
{"learn":[450.9001418],"iteration":932,"passed_time":2.519637559,"remaining_time":0.1809386029},
{"learn":[450.7363367],"iteration":933,"passed_time":2.52236447,"remaining_time":0.1782398876},
{"learn":[450.5369795],"iteration":934,"passed_time":2.52483517,"remaining_time":0.1755233006},
{"learn":[450.4876264],"iteration":935,"passed_time":2.527171326,"remaining_time":0.1727980394},
{"learn":[450.3963455],"iteration":936,"passed_time":2.529657568,"remaining_time":0.1700836999},
{"learn":[450.3166808],"iteration":937,"passed_time":2.532328853,"remaining_time":0.1673820777},
{"learn":[450.2027913],"iteration":938,"passed_time":2.5352121,"remaining_time":0.1646942898},
{"learn":[450.1358682],"iteration":939,"passed_time":2.53771855,"remaining_time":0.1619820351},
{"learn":[450.0059735],"iteration":940,"passed_time":2.54037121,"remaining_time":0.1592793851},
{"learn":[449.9423574],"iteration":941,"passed_time":2.543036204,"remaining_time":0.1565776007},
{"learn":[449.8527029],"iteration":942,"passed_time":2.545753115,"remaining_time":0.1538790324},
{"learn":[449.7910551],"iteration":943,"passed_time":2.548288065,"remaining_time":0.151169631},
{"learn":[449.7029319],"iteration":944,"passed_time":2.550890767,"remaining_time":0.148464542},
{"learn":[449.6456448],"iteration":945,"passed_time":2.553462134,"remaining_time":0.1457578808},
{"learn":[449.6005682],"iteration":946,"passed_time":2.556081376,"remaining_time":0.1430541847},
{"learn":[449.4844143],"iteration":947,"passed_time":2.55867187,"remaining_time":0.1403490899},
{"learn":[449.3430059],"iteration":948,"passed_time":2.56142224,"remaining_time":0.1376528285},
{"learn":[449.2150712],"iteration":949,"passed_time":2.564343779,"remaining_time":0.134965462},
{"learn":[449.1224687],"iteration":950,"passed_time":2.567099732,"remaining_time":0.1322690714},
{"learn":[449.020941],"iteration":951,"passed_time":2.569689849,"remaining_time":0.1295641941},
{"learn":[448.8748],"iteration":952,"passed_time":2.5723318,"remaining_time":0.126862114},
{"learn":[448.7892698],"iteration":953,"passed_time":2.574893959,"remaining_time":0.1241563125},
{"learn":[448.6363951],"iteration":954,"passed_time":2.577825623,"remaining_time":0.1214682231},
{"learn":[448.5484265],"iteration":955,"passed_time":2.580234613,"remaining_time":0.118755568},
{"learn":[448.4197095],"iteration":956,"passed_time":2.582718896,"remaining_time":0.1160469305},
{"learn":[448.3421563],"iteration":957,"passed_time":2.585624059,"remaining_time":0.1133572135},
{"learn":[448.2547281],"iteration":958,"passed_time":2.588582223,"remaining_time":0.110669313},
{"learn":[448.1400915],"iteration":959,"passed_time":2.591298634,"remaining_time":0.1079707764},
{"learn":[448.041976],"iteration":960,"passed_time":2.593979587,"remaining_time":0.1052707637},
{"learn":[448.0227195],"iteration":961,"passed_time":2.596620539,"remaining_time":0.1025692105},
{"learn":[447.870877],"iteration":962,"passed_time":2.599277907,"remaining_time":0.09986841387},
{"learn":[447.8352055],"iteration":963,"passed_time":2.602020943,"remaining_time":0.09717090659},
{"learn":[447.7198688],"iteration":964,"passed_time":2.604746396,"remaining_time":0.09447266722},
{"learn":[447.6352321],"iteration":965,"passed_time":2.60784502,"remaining_time":0.09178750589},
{"learn":[447.5444186],"iteration":966,"passed_time":2.610569098,"remaining_time":0.08908870759},
{"learn":[447.411688],"iteration":967,"passed_time":2.613250468,"remaining_time":0.08638844521},
{"learn":[447.3959127],"iteration":968,"passed_time":2.615963838,"remaining_time":0.08368924558},
{"learn":[447.3637371],"iteration":969,"passed_time":2.618662748,"remaining_time":0.08098956954},
{"learn":[447.240731],"iteration":970,"passed_time":2.621505495,"remaining_time":0.07829419089},
{"learn":[447.2099012],"iteration":971,"passed_time":2.623765941,"remaining_time":0.07558173492},
{"learn":[447.1826124],"iteration":972,"passed_time":2.626416268,"remaining_time":0.07288102696},
{"learn":[447.0625344],"iteration":973,"passed_time":2.629236596,"remaining_time":0.07018496047},
{"learn":[446.9091446],"iteration":974,"passed_time":2.63191634,"remaining_time":0.06748503435},
{"learn":[446.7520958],"iteration":975,"passed_time":2.63443479,"remaining_time":0.06478118336},
{"learn":[446.6535803],"iteration":976,"passed_time":2.637314244,"remaining_time":0.06208621046},
{"learn":[446.5741102],"iteration":977,"passed_time":2.640063947,"remaining_time":0.05938794154},
{"learn":[446.4770393],"iteration":978,"passed_time":2.642831858,"remaining_time":0.05668995814},
{"learn":[446.324877],"iteration":979,"passed_time":2.645696146,"remaining_time":0.0539937989},
{"learn":[446.3044917],"iteration":980,"passed_time":2.648163429,"remaining_time":0.05128960769},
{"learn":[446.2432454],"iteration":981,"passed_time":2.650599378,"remaining_time":0.04858532465},
{"learn":[446.2119995],"iteration":982,"passed_time":2.652962576,"remaining_time":0.04588032939},
{"learn":[446.1858072],"iteration":983,"passed_time":2.655518318,"remaining_time":0.04317915964},
{"learn":[446.1613249],"iteration":984,"passed_time":2.658020184,"remaining_time":0.04047746473},
{"learn":[446.0155534],"iteration":985,"passed_time":2.660331256,"remaining_time":0.0377734661},
{"learn":[445.9675845],"iteration":986,"passed_time":2.662562076,"remaining_time":0.03506920668},
{"learn":[445.9047137],"iteration":987,"passed_time":2.665307238,"remaining_time":0.03237215268},
{"learn":[445.8425153],"iteration":988,"passed_time":2.667940189,"remaining_time":0.02967375337},
{"learn":[445.75515],"iteration":989,"passed_time":2.670468806,"remaining_time":0.02697443238},
{"learn":[445.7272132],"iteration":990,"passed_time":2.673126341,"remaining_time":0.02427662671},
{"learn":[445.6347681],"iteration":991,"passed_time":2.675526415,"remaining_time":0.02157682593},
{"learn":[445.5012313],"iteration":992,"passed_time":2.678111366,"remaining_time":0.01887893209},
{"learn":[445.3927945],"iteration":993,"passed_time":2.680758984,"remaining_time":0.01618164377},
{"learn":[445.3395566],"iteration":994,"passed_time":2.683596396,"remaining_time":0.01348540903},
{"learn":[445.2821711],"iteration":995,"passed_time":2.685920302,"remaining_time":0.01078682852},
{"learn":[445.2496793],"iteration":996,"passed_time":2.687816619,"remaining_time":0.008087712997},
{"learn":[445.189558],"iteration":997,"passed_time":2.689884772,"remaining_time":0.005390550645},
{"learn":[445.1214031],"iteration":998,"passed_time":2.692185969,"remaining_time":0.00269488085},
{"learn":[444.9932371],"iteration":999,"passed_time":2.694367664,"remaining_time":0}
]}eration":999,"passed_time":2.662507319,"remaining_time":0}
]}